[
    {
        "canal": "24/7CanaldeNoticias.ar",
        "evento": "Trasnoche de 24/7",
        "hora_inicio": "00:00",
        "hora_fin": "06:00",
        "progreso": 37
    },
    {
        "canal": "A24.ar",
        "evento": "TeveCompras",
        "hora_inicio": "02:00",
        "hora_fin": "03:00",
        "progreso": 22
    },
    {
        "canal": "AMC.ar",
        "evento": "Crepúsculo: Twilight",
        "hora_inicio": "01:55",
        "hora_fin": "04:10",
        "progreso": 13
    },
    {
        "canal": "AmericaSports.ar",
        "evento": "El escape del caburé",
        "hora_inicio": "02:00",
        "hora_fin": "03:00",
        "progreso": 22
    },
    {
        "canal": "AmericaTV.ar",
        "evento": "Pasión de sábado",
        "hora_inicio": "00:30",
        "hora_fin": "07:00",
        "progreso": 26
    },
    {
        "canal": "ArgentinisimaSatelital.ar",
        "evento": "Argentinisima satelital",
        "hora_inicio": "00:00",
        "hora_fin": "03:00",
        "progreso": 74
    },
    {
        "canal": "Atreseries.ar",
        "evento": "Pop Up: Aquí no hay quien viva",
        "hora_inicio": "01:28",
        "hora_fin": "02:33",
        "progreso": 70
    },
    {
        "canal": "AXN.ar",
        "evento": "Hawaii-Five-O",
        "hora_inicio": "01:44",
        "hora_fin": "02:34",
        "progreso": 59
    },
    {
        "canal": "BabyTV.ar",
        "evento": "Las melodías nocturnas de Baby TV",
        "hora_inicio": "02:00",
        "hora_fin": "02:30",
        "progreso": 45
    },
    {
        "canal": "Bloomberg.ar",
        "evento": "Bloomberg Primer",
        "hora_inicio": "02:00",
        "hora_fin": "02:30",
        "progreso": 45
    },
    {
        "canal": "C5N.ar",
        "evento": "Right Now",
        "hora_inicio": "02:00",
        "hora_fin": "02:30",
        "progreso": 45
    },
    {
        "canal": "Canal21.ar",
        "evento": "Encuentro, música y oración",
        "hora_inicio": "02:00",
        "hora_fin": "03:00",
        "progreso": 22
    },
    {
        "canal": "Canal26.ar",
        "evento": "Resumen 26",
        "hora_inicio": "23:30",
        "hora_fin": "08:00",
        "progreso": 32
    },
    {
        "canal": "CanalDeLaCiudad.ar",
        "evento": "Puro Heavy",
        "hora_inicio": "00:00",
        "hora_fin": "03:00",
        "progreso": 74
    },
    {
        "canal": "CanalDeLaMusica.ar",
        "evento": "El valor de tus joyas",
        "hora_inicio": "02:00",
        "hora_fin": "02:30",
        "progreso": 45
    },
    {
        "canal": "CanalRural.ar",
        "evento": "Saber rural",
        "hora_inicio": "02:00",
        "hora_fin": "02:30",
        "progreso": 45
    },
    {
        "canal": "CartoonNetwork.ar",
        "evento": "Escandalosos",
        "hora_inicio": "02:10",
        "hora_fin": "02:20",
        "progreso": 37
    },
    {
        "canal": "CineAr.ar",
        "evento": "Mario on Tour",
        "hora_inicio": "02:00",
        "hora_fin": "04:00",
        "progreso": 11
    },
    {
        "canal": "Cinecanal.ar",
        "evento": "Nunca, rara vez, a veces, siempre",
        "hora_inicio": "00:33",
        "hora_fin": "02:36",
        "progreso": 81
    },
    {
        "canal": "Cinelatino.ar",
        "evento": "El señor de los cuernos",
        "hora_inicio": "01:25",
        "hora_fin": "02:55",
        "progreso": 54
    },
    {
        "canal": "Cinemax(Sur).ar",
        "evento": "La mejor noche de tu vida",
        "hora_inicio": "01:49",
        "hora_fin": "03:27",
        "progreso": 25
    },
    {
        "canal": "Cinemax.ar",
        "evento": "El juego de la fortuna",
        "hora_inicio": "02:11",
        "hora_fin": "04:31",
        "progreso": 1
    },
    {
        "canal": "CiudadMagazine.ar",
        "evento": "Construyendo sueños TV",
        "hora_inicio": "02:00",
        "hora_fin": "02:30",
        "progreso": 45
    },
    {
        "canal": "CN23.ar",
        "evento": "CN 23",
        "hora_inicio": "02:00",
        "hora_fin": "03:00",
        "progreso": 22
    },
    {
        "canal": "CNN.ar",
        "evento": "CNN Newsroom",
        "hora_inicio": "02:00",
        "hora_fin": "02:30",
        "progreso": 45
    },
    {
        "canal": "CNNenEspanol.ar",
        "evento": "Showbiz",
        "hora_inicio": "02:00",
        "hora_fin": "02:30",
        "progreso": 45
    },
    {
        "canal": "ComedyCentral.ar",
        "evento": "South Park",
        "hora_inicio": "02:10",
        "hora_fin": "02:35",
        "progreso": 15
    },
    {
        "canal": "ConexionEducativa.ar",
        "evento": "Conexión educativa",
        "hora_inicio": "00:00",
        "hora_fin": "03:00",
        "progreso": 74
    },
    {
        "canal": "ConstruirTV.ar",
        "evento": "Incluidos",
        "hora_inicio": "01:00",
        "hora_fin": "02:30",
        "progreso": 81
    },
    {
        "canal": "CronicaTV.ar",
        "evento": "Iglesia de la ciudad",
        "hora_inicio": "01:30",
        "hora_fin": "02:30",
        "progreso": 72
    },
    {
        "canal": "Discovery.ar",
        "evento": "Cámara policial",
        "hora_inicio": "02:10",
        "hora_fin": "02:56",
        "progreso": 8
    },
    {
        "canal": "DiscoveryChannel.ar",
        "evento": "Cámara policial",
        "hora_inicio": "02:10",
        "hora_fin": "02:56",
        "progreso": 8
    },
    {
        "canal": "DiscoveryHomeAndHealth.ar",
        "evento": "Sala de emergencias: historias inéditas",
        "hora_inicio": "02:03",
        "hora_fin": "02:55",
        "progreso": 20
    },
    {
        "canal": "DiscoveryKids.ar",
        "evento": "Héroes y hermanos",
        "hora_inicio": "02:13",
        "hora_fin": "02:25",
        "progreso": 6
    },
    {
        "canal": "DiscoveryTurbo.ar",
        "evento": "Garaje Goblin",
        "hora_inicio": "01:30",
        "hora_fin": "02:23",
        "progreso": 82
    },
    {
        "canal": "DisneyChannel.ar",
        "evento": "The Owl House - La Casa Búho",
        "hora_inicio": "02:03",
        "hora_fin": "02:25",
        "progreso": 49
    },
    {
        "canal": "DisneyJunior.ar",
        "evento": "Star Wars: aventuras de jóvenes Jedi",
        "hora_inicio": "02:01",
        "hora_fin": "02:26",
        "progreso": 51
    },
    {
        "canal": "ElGarageTv.ar",
        "evento": "El potro 4x4",
        "hora_inicio": "02:00",
        "hora_fin": "02:30",
        "progreso": 45
    },
    {
        "canal": "ElGourmet.ar",
        "evento": "Con vistas al mar",
        "hora_inicio": "02:00",
        "hora_fin": "02:30",
        "progreso": 45
    },
    {
        "canal": "ELNueve.ar",
        "evento": "Cierre de transmisión",
        "hora_inicio": "02:00",
        "hora_fin": "05:30",
        "progreso": 6
    },
    {
        "canal": "ELTrece.ar",
        "evento": "Fin de transmisión",
        "hora_inicio": "00:15",
        "hora_fin": "08:45",
        "progreso": 23
    },
    {
        "canal": "Encuentro.ar",
        "evento": "Espíritu Newbery",
        "hora_inicio": "02:00",
        "hora_fin": "02:30",
        "progreso": 45
    },
    {
        "canal": "ESPN.ar",
        "evento": "ESPN Mundial",
        "hora_inicio": "02:00",
        "hora_fin": "04:00",
        "progreso": 11
    },
    {
        "canal": "ESPN2.ar",
        "evento": "Bélgica vs. Argentina",
        "hora_inicio": "01:00",
        "hora_fin": "02:45",
        "progreso": 70
    },
    {
        "canal": "ESPN3.ar",
        "evento": "Seattle Storm vs. Phoenix Mercury",
        "hora_inicio": "02:00",
        "hora_fin": "04:00",
        "progreso": 11
    },
    {
        "canal": "ESPN4.ar",
        "evento": "Newman vs. CASI",
        "hora_inicio": "02:00",
        "hora_fin": "04:00",
        "progreso": 11
    },
    {
        "canal": "ESPNExtra.ar",
        "evento": "El show de la Fórmula 1",
        "hora_inicio": "02:00",
        "hora_fin": "03:00",
        "progreso": 22
    },
    {
        "canal": "ESPNSur.ar",
        "evento": "ESPN Mundial",
        "hora_inicio": "23:00",
        "hora_fin": "03:00",
        "progreso": 80
    },
    {
        "canal": "ESPNSur2.ar",
        "evento": "Hockey sobre césped FIH Pro League femenina",
        "hora_inicio": "02:00",
        "hora_fin": "03:45",
        "progreso": 13
    },
    {
        "canal": "ESPNSur3.ar",
        "evento": "Baloncesto WNBA",
        "hora_inicio": "01:00",
        "hora_fin": "03:00",
        "progreso": 61
    },
    {
        "canal": "ESPNSur4.ar",
        "evento": "Rugby Argentino Torneo de la URBA",
        "hora_inicio": "01:00",
        "hora_fin": "03:00",
        "progreso": 61
    },
    {
        "canal": "EuropaEuropa.ar",
        "evento": "El fin de la verdad",
        "hora_inicio": "02:05",
        "hora_fin": "04:05",
        "progreso": 7
    },
    {
        "canal": "EWTN.ar",
        "evento": "Cocina franciscana",
        "hora_inicio": "02:00",
        "hora_fin": "02:30",
        "progreso": 45
    },
    {
        "canal": "filmAndarts.ar",
        "evento": "El ilusionista",
        "hora_inicio": "00:25",
        "hora_fin": "02:30",
        "progreso": 87
    },
    {
        "canal": "FOX Sports",
        "evento": "Corinthians (Bra) vs. Platense (Arg)",
        "hora_inicio": "02:00",
        "hora_fin": "04:00",
        "progreso": 11
    },
    {
        "canal": "FOXSports2.ar",
        "evento": "Show Turf",
        "hora_inicio": "02:00",
        "hora_fin": "03:00",
        "progreso": 22
    },
    {
        "canal": "FOXSports3.ar",
        "evento": "Media cancha",
        "hora_inicio": "02:00",
        "hora_fin": "06:00",
        "progreso": 5
    },
    {
        "canal": "FOXSportsConoSur.ar",
        "evento": "Corinthians (Bra) vs. Platense (Arg)",
        "hora_inicio": "02:00",
        "hora_fin": "04:00",
        "progreso": 11
    },
    {
        "canal": "France24enEspanol.ar",
        "evento": "Boleto de vuelta",
        "hora_inicio": "02:10",
        "hora_fin": "02:29",
        "progreso": 19
    },
    {
        "canal": "FX.ar",
        "evento": "El hombre invisible",
        "hora_inicio": "23:59",
        "hora_fin": "02:29",
        "progreso": 89
    },
    {
        "canal": "GaliciaTV.ar",
        "evento": "O termómetro",
        "hora_inicio": "02:00",
        "hora_fin": "04:00",
        "progreso": 11
    },
    {
        "canal": "Golden.ar",
        "evento": "Un detective en el Kinder",
        "hora_inicio": "00:38",
        "hora_fin": "02:42",
        "progreso": 77
    },
    {
        "canal": "GoldenEdge.ar",
        "evento": "Encontré al Diablo",
        "hora_inicio": "01:38",
        "hora_fin": "04:18",
        "progreso": 22
    },
    {
        "canal": "GolfChannel.ar",
        "evento": "Rick Shiels - Part 2",
        "hora_inicio": "02:00",
        "hora_fin": "02:30",
        "progreso": 45
    },
    {
        "canal": "HAPSATV.ar",
        "evento": "Turf en vivo - Palermo, San Isidro y La Plata",
        "hora_inicio": "00:00",
        "hora_fin": "04:00",
        "progreso": 55
    },
    {
        "canal": "HBO.ar",
        "evento": "Juego de ladrones 2",
        "hora_inicio": "01:10",
        "hora_fin": "03:25",
        "progreso": 47
    },
    {
        "canal": "HBO2.ar",
        "evento": "La liga de la justicia",
        "hora_inicio": "01:55",
        "hora_fin": "04:00",
        "progreso": 15
    },
    {
        "canal": "HBOFamily.ar",
        "evento": "Hombres de negro 3",
        "hora_inicio": "01:54",
        "hora_fin": "03:41",
        "progreso": 18
    },
    {
        "canal": "HBOMundi.ar",
        "evento": "Cónclave",
        "hora_inicio": "01:20",
        "hora_fin": "03:25",
        "progreso": 43
    },
    {
        "canal": "HBOOeste.ar",
        "evento": "Araña asesina",
        "hora_inicio": "01:00",
        "hora_fin": "02:38",
        "progreso": 75
    },
    {
        "canal": "HBOPlus(Panamericano).ar",
        "evento": "Máquinas mortales",
        "hora_inicio": "01:55",
        "hora_fin": "04:10",
        "progreso": 13
    },
    {
        "canal": "HBOPlusEste.ar",
        "evento": "Máquinas mortales",
        "hora_inicio": "01:55",
        "hora_fin": "04:10",
        "progreso": 13
    },
    {
        "canal": "HBOPop.ar",
        "evento": "Novio por una noche",
        "hora_inicio": "01:45",
        "hora_fin": "03:30",
        "progreso": 27
    },
    {
        "canal": "HBOSignature.ar",
        "evento": "Bessie",
        "hora_inicio": "02:03",
        "hora_fin": "04:00",
        "progreso": 9
    },
    {
        "canal": "HBOXtreme(Panamericano).ar",
        "evento": "El justiciero",
        "hora_inicio": "00:00",
        "hora_fin": "02:15",
        "progreso": 99
    },
    {
        "canal": "HBOXtreme.ar",
        "evento": "El justiciero",
        "hora_inicio": "00:00",
        "hora_fin": "02:15",
        "progreso": 99
    },
    {
        "canal": "HGTV.ar",
        "evento": "Nuestro hogar en la montaña",
        "hora_inicio": "01:58",
        "hora_fin": "02:20",
        "progreso": 71
    },
    {
        "canal": "HispanTV.ar",
        "evento": "La guerra de El Líbano, vida cotidiana",
        "hora_inicio": "02:00",
        "hora_fin": "02:30",
        "progreso": 45
    },
    {
        "canal": "History.ar",
        "evento": "El precio de la historia en la carretera",
        "hora_inicio": "01:36",
        "hora_fin": "02:20",
        "progreso": 85
    },
    {
        "canal": "History2.ar",
        "evento": "Gigantes de la industria",
        "hora_inicio": "01:10",
        "hora_fin": "02:45",
        "progreso": 67
    },
    {
        "canal": "HolaTV.ar",
        "evento": "La casa de modas",
        "hora_inicio": "02:00",
        "hora_fin": "03:30",
        "progreso": 15
    },
    {
        "canal": "HTV.ar",
        "evento": "HTV",
        "hora_inicio": "01:00",
        "hora_fin": "09:00",
        "progreso": 15
    },
    {
        "canal": "InvestigationDiscovery.ar",
        "evento": "Asesinatos en Silicon Valley",
        "hora_inicio": "02:12",
        "hora_fin": "02:59",
        "progreso": 3
    },
    {
        "canal": "LasEstrellas.ar",
        "evento": "Mujer, casos de la vida real",
        "hora_inicio": "01:10",
        "hora_fin": "03:15",
        "progreso": 51
    },
    {
        "canal": "LN+.ar",
        "evento": "La robineta",
        "hora_inicio": "01:00",
        "hora_fin": "06:00",
        "progreso": 24
    },
    {
        "canal": "MasChic.ar",
        "evento": "El terror",
        "hora_inicio": "01:50",
        "hora_fin": "02:40",
        "progreso": 47
    },
    {
        "canal": "Metro.ar",
        "evento": "En forma - Medicina farmacéutica",
        "hora_inicio": "02:00",
        "hora_fin": "02:30",
        "progreso": 45
    },
    {
        "canal": "MTV.ar",
        "evento": "Geordie Shore",
        "hora_inicio": "02:05",
        "hora_fin": "02:50",
        "progreso": 19
    },
    {
        "canal": "Musictop.ar",
        "evento": "MusicTop",
        "hora_inicio": "02:00",
        "hora_fin": "03:00",
        "progreso": 22
    },
    {
        "canal": "NationalGeographic.ar",
        "evento": "Mayday: catástrofes aéreas",
        "hora_inicio": "02:03",
        "hora_fin": "02:47",
        "progreso": 24
    },
    {
        "canal": "NBATV.ar",
        "evento": "Draft Preview",
        "hora_inicio": "02:00",
        "hora_fin": "03:00",
        "progreso": 22
    },
    {
        "canal": "NetTV.ar",
        "evento": "Desafío 10 años menos",
        "hora_inicio": "02:00",
        "hora_fin": "02:30",
        "progreso": 45
    },
    {
        "canal": "NickJr..ar",
        "evento": "Barbapapá",
        "hora_inicio": "02:10",
        "hora_fin": "02:35",
        "progreso": 15
    },
    {
        "canal": "Pakapaka.ar",
        "evento": "Cuentos del árbol",
        "hora_inicio": "02:00",
        "hora_fin": "02:45",
        "progreso": 30
    },
    {
        "canal": "Pasiones.ar",
        "evento": "La suerte de Loli",
        "hora_inicio": "02:00",
        "hora_fin": "03:00",
        "progreso": 22
    },
    {
        "canal": "PenthouseGold.ar",
        "evento": "Mis fantasías extremas",
        "hora_inicio": "02:06",
        "hora_fin": "04:00",
        "progreso": 6
    },
    {
        "canal": "Playboy.ar",
        "evento": "Labios calientes",
        "hora_inicio": "02:02",
        "hora_fin": "02:51",
        "progreso": 24
    },
    {
        "canal": "Quiero.ar",
        "evento": "Los 60 +",
        "hora_inicio": "01:00",
        "hora_fin": "05:00",
        "progreso": 30
    },
    {
        "canal": "RaiItalia.ar",
        "evento": "TG1",
        "hora_inicio": "02:00",
        "hora_fin": "02:15",
        "progreso": 91
    },
    {
        "canal": "RussiaToday.ar",
        "evento": "Ahí les va",
        "hora_inicio": "02:00",
        "hora_fin": "02:30",
        "progreso": 45
    },
    {
        "canal": "Sony.ar",
        "evento": "Sin escape",
        "hora_inicio": "00:35",
        "hora_fin": "02:30",
        "progreso": 85
    },
    {
        "canal": "Space.ar",
        "evento": "Aves de presa y la fantabulosa emancipación de una Harley Quinn",
        "hora_inicio": "00:19",
        "hora_fin": "02:15",
        "progreso": 98
    },
    {
        "canal": "StarChannel.ar",
        "evento": "El último duelo",
        "hora_inicio": "23:52",
        "hora_fin": "02:41",
        "progreso": 83
    },
    {
        "canal": "StudioUniversal.ar",
        "evento": "Sicario",
        "hora_inicio": "01:25",
        "hora_fin": "03:35",
        "progreso": 37
    },
    {
        "canal": "TCM.ar",
        "evento": "Rojo",
        "hora_inicio": "01:01",
        "hora_fin": "02:50",
        "progreso": 66
    },
    {
        "canal": "TECtv.ar",
        "evento": "TecTV",
        "hora_inicio": "00:00",
        "hora_fin": "04:00",
        "progreso": 55
    },
    {
        "canal": "Telediario.ar",
        "evento": "Resumen de noticias",
        "hora_inicio": "02:00",
        "hora_fin": "04:00",
        "progreso": 11
    },
    {
        "canal": "Telefe.ar",
        "evento": "DirecTV - DGO Presentan: Espiando la casa",
        "hora_inicio": "02:00",
        "hora_fin": "03:00",
        "progreso": 22
    },
    {
        "canal": "TelefeCordoba.ar",
        "evento": "Fin de transmisión",
        "hora_inicio": "01:15",
        "hora_fin": "09:00",
        "progreso": 12
    },
    {
        "canal": "TelefeRosario.ar",
        "evento": "Pare de sufrir",
        "hora_inicio": "01:45",
        "hora_fin": "02:15",
        "progreso": 95
    },
    {
        "canal": "TelefeSantaFe.ar",
        "evento": "Fin de transmisión",
        "hora_inicio": "01:00",
        "hora_fin": "10:30",
        "progreso": 12
    },
    {
        "canal": "Telehit.ar",
        "evento": "Dale Play",
        "hora_inicio": "02:00",
        "hora_fin": "03:00",
        "progreso": 22
    },
    {
        "canal": "Telemax.ar",
        "evento": "Documentales de interés general",
        "hora_inicio": "00:00",
        "hora_fin": "06:00",
        "progreso": 37
    },
    {
        "canal": "teleSUR.ar",
        "evento": "Enredados",
        "hora_inicio": "02:00",
        "hora_fin": "02:30",
        "progreso": 45
    },
    {
        "canal": "TelevisionPublica.ar",
        "evento": "Fin de transmisión",
        "hora_inicio": "01:00",
        "hora_fin": "06:45",
        "progreso": 21
    },
    {
        "canal": "TierraMiaTV.ar",
        "evento": "TierraMia TV",
        "hora_inicio": "02:00",
        "hora_fin": "03:00",
        "progreso": 22
    },
    {
        "canal": "TLC.ar",
        "evento": "Todo en 90 días: ¿Felices por siempre?",
        "hora_inicio": "00:49",
        "hora_fin": "02:18",
        "progreso": 95
    },
    {
        "canal": "TLNovelas.ar",
        "evento": "La rosa de Guadalupe",
        "hora_inicio": "02:00",
        "hora_fin": "02:50",
        "progreso": 27
    },
    {
        "canal": "TN.ar",
        "evento": "TN especial",
        "hora_inicio": "01:30",
        "hora_fin": "02:30",
        "progreso": 72
    },
    {
        "canal": "TNTSeries.ar",
        "evento": "El mentalista",
        "hora_inicio": "02:11",
        "hora_fin": "02:54",
        "progreso": 6
    },
    {
        "canal": "Tooncast.ar",
        "evento": "Don Gato y su pandilla",
        "hora_inicio": "02:08",
        "hora_fin": "02:33",
        "progreso": 23
    },
    {
        "canal": "TurismoVisionArgentina.ar",
        "evento": "Turismo Visión Argentina",
        "hora_inicio": "00:00",
        "hora_fin": "03:00",
        "progreso": 74
    },
    {
        "canal": "TV5.ar",
        "evento": "La Fête de la musique",
        "hora_inicio": "22:56",
        "hora_fin": "02:48",
        "progreso": 85
    },
    {
        "canal": "TVCiudad.ar",
        "evento": "Autores en vivo",
        "hora_inicio": "01:30",
        "hora_fin": "02:22",
        "progreso": 84
    },
    {
        "canal": "TVE.ar",
        "evento": "Tendido cero",
        "hora_inicio": "02:10",
        "hora_fin": "03:00",
        "progreso": 7
    },
    {
        "canal": "TVGlobo.ar",
        "evento": "Papo de segunda",
        "hora_inicio": "02:00",
        "hora_fin": "03:10",
        "progreso": 19
    },
    {
        "canal": "TVNacionalUruguay.ar",
        "evento": "La ruta de Gardel en Uruguay",
        "hora_inicio": "02:00",
        "hora_fin": "03:00",
        "progreso": 22
    },
    {
        "canal": "TVNCHILE.ar",
        "evento": "El hacedor de hambre",
        "hora_inicio": "01:30",
        "hora_fin": "02:30",
        "progreso": 72
    },
    {
        "canal": "TVPublica.ar",
        "evento": "Fin de transmisión",
        "hora_inicio": "01:00",
        "hora_fin": "06:45",
        "progreso": 21
    },
    {
        "canal": "TyCSports.ar",
        "evento": "Copa Mundial de la FIFA 26",
        "hora_inicio": "02:00",
        "hora_fin": "03:00",
        "progreso": 22
    },
    {
        "canal": "TyCSports2.ar",
        "evento": "TyC Sports 2",
        "hora_inicio": "00:00",
        "hora_fin": "10:00",
        "progreso": 22
    },
    {
        "canal": "UniversalTV.ar",
        "evento": "La ley y el orden: crimen organizado",
        "hora_inicio": "02:00",
        "hora_fin": "02:50",
        "progreso": 27
    },
    {
        "canal": "UruguayNaturalTV.ar",
        "evento": "Uruguay Natural TV",
        "hora_inicio": "00:00",
        "hora_fin": "04:00",
        "progreso": 55
    },
    {
        "canal": "Venus.ar",
        "evento": "Big Boobs Are a Massive Distraction",
        "hora_inicio": "01:58",
        "hora_fin": "03:28",
        "progreso": 17
    },
    {
        "canal": "Volver.ar",
        "evento": "El escuadrón azul",
        "hora_inicio": "01:45",
        "hora_fin": "03:00",
        "progreso": 38
    },
    {
        "canal": "VTV.ar",
        "evento": "Tabaré vs. Larre Borges",
        "hora_inicio": "01:00",
        "hora_fin": "03:00",
        "progreso": 61
    },
    {
        "canal": "WarnerChannel.ar",
        "evento": "The Big Bang Theory",
        "hora_inicio": "02:06",
        "hora_fin": "02:29",
        "progreso": 33
    },
    {
        "canal": "ZooMoo.ar",
        "evento": "El show de los animales con Apestoso y Jake",
        "hora_inicio": "02:00",
        "hora_fin": "02:30",
        "progreso": 45
    }
]