[
    {
        "canal": "24/7CanaldeNoticias.ar",
        "evento": "Informe semanal",
        "hora_inicio": "09:00",
        "hora_fin": "11:00",
        "progreso": 26
    },
    {
        "canal": "A24.ar",
        "evento": "Vivo el sábado",
        "hora_inicio": "07:00",
        "hora_fin": "14:00",
        "progreso": 36
    },
    {
        "canal": "AandE.ar",
        "evento": "No Data",
        "hora_inicio": "09:00",
        "hora_fin": "10:00",
        "progreso": 52
    },
    {
        "canal": "AMC.ar",
        "evento": "Infomerciales",
        "hora_inicio": "09:30",
        "hora_fin": "10:00",
        "progreso": 5
    },
    {
        "canal": "AmericaSports.ar",
        "evento": "Infomerciales",
        "hora_inicio": "07:00",
        "hora_fin": "10:00",
        "progreso": 84
    },
    {
        "canal": "AmericaTV.ar",
        "evento": "TeveCompras",
        "hora_inicio": "08:00",
        "hora_fin": "10:00",
        "progreso": 76
    },
    {
        "canal": "AnimalPlanet.ar",
        "evento": "Refugio en el granero",
        "hora_inicio": "09:21",
        "hora_fin": "10:17",
        "progreso": 19
    },
    {
        "canal": "ArgentinisimaSatelital.ar",
        "evento": "Argentinisima satelital",
        "hora_inicio": "09:00",
        "hora_fin": "12:00",
        "progreso": 17
    },
    {
        "canal": "Atreseries.ar",
        "evento": "El secreto de Puente Viejo",
        "hora_inicio": "09:25",
        "hora_fin": "10:30",
        "progreso": 10
    },
    {
        "canal": "AXN.ar",
        "evento": "TeveCompras",
        "hora_inicio": "09:30",
        "hora_fin": "10:00",
        "progreso": 5
    },
    {
        "canal": "BabyTV.ar",
        "evento": "La hora del arte, la actividad y la música",
        "hora_inicio": "09:30",
        "hora_fin": "10:00",
        "progreso": 5
    },
    {
        "canal": "Bloomberg.ar",
        "evento": "Bloomberg This Weekend",
        "hora_inicio": "08:00",
        "hora_fin": "11:00",
        "progreso": 50
    },
    {
        "canal": "C5N.ar",
        "evento": "Argentina en vivo",
        "hora_inicio": "09:00",
        "hora_fin": "12:00",
        "progreso": 17
    },
    {
        "canal": "Canal21.ar",
        "evento": "Punto convergente TV",
        "hora_inicio": "09:00",
        "hora_fin": "10:00",
        "progreso": 52
    },
    {
        "canal": "Canal26.ar",
        "evento": "Fin de semana",
        "hora_inicio": "08:00",
        "hora_fin": "10:00",
        "progreso": 76
    },
    {
        "canal": "CanalDeLaCiudad.ar",
        "evento": "Nuevo cine Argentino",
        "hora_inicio": "09:00",
        "hora_fin": "11:00",
        "progreso": 26
    },
    {
        "canal": "CanalDeLaMusica.ar",
        "evento": "K-Pop",
        "hora_inicio": "09:30",
        "hora_fin": "10:00",
        "progreso": 5
    },
    {
        "canal": "CanalRural.ar",
        "evento": "Cátedra avícola y agropecuaria",
        "hora_inicio": "09:30",
        "hora_fin": "10:00",
        "progreso": 5
    },
    {
        "canal": "Cartoonito.ar",
        "evento": "No Data",
        "hora_inicio": "09:00",
        "hora_fin": "10:00",
        "progreso": 52
    },
    {
        "canal": "CartoonNetwork.ar",
        "evento": "Escandalositos",
        "hora_inicio": "09:24",
        "hora_fin": "09:36",
        "progreso": 63
    },
    {
        "canal": "CineAr.ar",
        "evento": "La afinadora de árboles",
        "hora_inicio": "08:00",
        "hora_fin": "10:00",
        "progreso": 76
    },
    {
        "canal": "Cinecanal.ar",
        "evento": "La increíble vida de Walter Mitty",
        "hora_inicio": "08:37",
        "hora_fin": "10:59",
        "progreso": 38
    },
    {
        "canal": "Cinelatino.ar",
        "evento": "No más muertes en la frontera",
        "hora_inicio": "09:00",
        "hora_fin": "10:40",
        "progreso": 31
    },
    {
        "canal": "Cinemax(Sur).ar",
        "evento": "Black Adam",
        "hora_inicio": "09:07",
        "hora_fin": "11:19",
        "progreso": 18
    },
    {
        "canal": "Cinemax.ar",
        "evento": "Secretos íntimos",
        "hora_inicio": "05:38",
        "hora_fin": "10:02",
        "progreso": 88
    },
    {
        "canal": "CiudadMagazine.ar",
        "evento": "El Chavo",
        "hora_inicio": "09:30",
        "hora_fin": "10:32",
        "progreso": 2
    },
    {
        "canal": "CN23.ar",
        "evento": "CN 23",
        "hora_inicio": "09:00",
        "hora_fin": "10:00",
        "progreso": 52
    },
    {
        "canal": "CNN.ar",
        "evento": "Inside Africa",
        "hora_inicio": "07:30",
        "hora_fin": "13:30",
        "progreso": 33
    },
    {
        "canal": "CNNenEspanol.ar",
        "evento": "Globo economía",
        "hora_inicio": "09:30",
        "hora_fin": "10:00",
        "progreso": 5
    },
    {
        "canal": "ComedyCentral.ar",
        "evento": "Póquer de reinas",
        "hora_inicio": "09:30",
        "hora_fin": "09:55",
        "progreso": 6
    },
    {
        "canal": "ConexionEducativa.ar",
        "evento": "Conexión educativa",
        "hora_inicio": "09:00",
        "hora_fin": "12:00",
        "progreso": 17
    },
    {
        "canal": "ConstruirTV.ar",
        "evento": "Pobladores",
        "hora_inicio": "09:00",
        "hora_fin": "10:30",
        "progreso": 35
    },
    {
        "canal": "CronicaTV.ar",
        "evento": "Hoy es mejor",
        "hora_inicio": "08:00",
        "hora_fin": "11:00",
        "progreso": 50
    },
    {
        "canal": "Discovery.ar",
        "evento": "Supervivencia al desnudo",
        "hora_inicio": "08:49",
        "hora_fin": "09:38",
        "progreso": 87
    },
    {
        "canal": "DiscoveryChannel.ar",
        "evento": "Supervivencia al desnudo",
        "hora_inicio": "08:49",
        "hora_fin": "09:38",
        "progreso": 87
    },
    {
        "canal": "DiscoveryHomeAndHealth.ar",
        "evento": "A confirmar",
        "hora_inicio": "09:30",
        "hora_fin": "09:50",
        "progreso": 8
    },
    {
        "canal": "DiscoveryKids.ar",
        "evento": "Peppa Pig",
        "hora_inicio": "09:09",
        "hora_fin": "09:33",
        "progreso": 94
    },
    {
        "canal": "DiscoveryTurbo.ar",
        "evento": "El dúo mecánico",
        "hora_inicio": "08:52",
        "hora_fin": "09:43",
        "progreso": 77
    },
    {
        "canal": "DisneyChannel.ar",
        "evento": "Los Green en la gran ciudad",
        "hora_inicio": "09:30",
        "hora_fin": "09:59",
        "progreso": 5
    },
    {
        "canal": "DisneyJunior.ar",
        "evento": "Princesita Sofía",
        "hora_inicio": "09:30",
        "hora_fin": "10:02",
        "progreso": 5
    },
    {
        "canal": "DisneyXD.ar",
        "evento": "No Data",
        "hora_inicio": "09:00",
        "hora_fin": "10:00",
        "progreso": 52
    },
    {
        "canal": "Dreamworks.ar",
        "evento": "No Data",
        "hora_inicio": "09:00",
        "hora_fin": "10:00",
        "progreso": 52
    },
    {
        "canal": "E!.ar",
        "evento": "No Data",
        "hora_inicio": "09:00",
        "hora_fin": "10:00",
        "progreso": 52
    },
    {
        "canal": "ElGarageTv.ar",
        "evento": "American Dreams",
        "hora_inicio": "09:30",
        "hora_fin": "10:00",
        "progreso": 5
    },
    {
        "canal": "ElGourmet.ar",
        "evento": "Infomerciales",
        "hora_inicio": "09:30",
        "hora_fin": "10:00",
        "progreso": 5
    },
    {
        "canal": "ELNueve.ar",
        "evento": "Suterh con vos",
        "hora_inicio": "09:00",
        "hora_fin": "10:00",
        "progreso": 52
    },
    {
        "canal": "ELTrece.ar",
        "evento": "Plan TV",
        "hora_inicio": "09:00",
        "hora_fin": "10:00",
        "progreso": 52
    },
    {
        "canal": "Encuentro.ar",
        "evento": "Nacidos por escrito",
        "hora_inicio": "09:00",
        "hora_fin": "10:30",
        "progreso": 35
    },
    {
        "canal": "ESPN.ar",
        "evento": "ESPN Mundial",
        "hora_inicio": "07:00",
        "hora_fin": "11:00",
        "progreso": 63
    },
    {
        "canal": "ESPN2.ar",
        "evento": "SportsCenter+",
        "hora_inicio": "08:30",
        "hora_fin": "11:00",
        "progreso": 41
    },
    {
        "canal": "ESPN3.ar",
        "evento": "Semifinales",
        "hora_inicio": "07:00",
        "hora_fin": "11:00",
        "progreso": 63
    },
    {
        "canal": "ESPN4.ar",
        "evento": "Gran Premio de Bélgica, Carrera 1, Circuito de Spa-Francorchamps",
        "hora_inicio": "09:05",
        "hora_fin": "10:15",
        "progreso": 38
    },
    {
        "canal": "ESPNExtra.ar",
        "evento": "Compacto - Rugby Nations Championship",
        "hora_inicio": "09:30",
        "hora_fin": "10:30",
        "progreso": 2
    },
    {
        "canal": "ESPNSur.ar",
        "evento": "ESPN Mundial",
        "hora_inicio": "08:00",
        "hora_fin": "12:00",
        "progreso": 38
    },
    {
        "canal": "ESPNSur2.ar",
        "evento": "SportsCenter+",
        "hora_inicio": "09:30",
        "hora_fin": "12:00",
        "progreso": 1
    },
    {
        "canal": "ESPNSur3.ar",
        "evento": "Premier Padel",
        "hora_inicio": "08:00",
        "hora_fin": "12:00",
        "progreso": 38
    },
    {
        "canal": "ESPNSur4.ar",
        "evento": "Automovilismo FIA Fórmula 3",
        "hora_inicio": "09:05",
        "hora_fin": "10:05",
        "progreso": 44
    },
    {
        "canal": "EuropaEuropa.ar",
        "evento": "El ministro de propaganda",
        "hora_inicio": "07:40",
        "hora_fin": "10:05",
        "progreso": 76
    },
    {
        "canal": "EWTN.ar",
        "evento": "Misa diaria",
        "hora_inicio": "09:00",
        "hora_fin": "10:00",
        "progreso": 52
    },
    {
        "canal": "filmAndarts.ar",
        "evento": "Infomerciales",
        "hora_inicio": "09:30",
        "hora_fin": "10:00",
        "progreso": 5
    },
    {
        "canal": "FOX Sports",
        "evento": "Argentina vs. Uruguay",
        "hora_inicio": "09:00",
        "hora_fin": "10:00",
        "progreso": 52
    },
    {
        "canal": "FOXSports2.ar",
        "evento": "Upgrade Golf",
        "hora_inicio": "09:30",
        "hora_fin": "10:00",
        "progreso": 5
    },
    {
        "canal": "FOXSports3.ar",
        "evento": "Marketing Registrado Mundial",
        "hora_inicio": "09:00",
        "hora_fin": "10:00",
        "progreso": 52
    },
    {
        "canal": "FOXSportsConoSur.ar",
        "evento": "Argentina vs. Uruguay",
        "hora_inicio": "09:00",
        "hora_fin": "10:00",
        "progreso": 52
    },
    {
        "canal": "France24enEspanol.ar",
        "evento": "Noticias",
        "hora_inicio": "09:30",
        "hora_fin": "09:40",
        "progreso": 16
    },
    {
        "canal": "FX.ar",
        "evento": "No soy tu mami",
        "hora_inicio": "07:59",
        "hora_fin": "10:14",
        "progreso": 68
    },
    {
        "canal": "FXMovies.ar",
        "evento": "No Data",
        "hora_inicio": "09:00",
        "hora_fin": "10:00",
        "progreso": 52
    },
    {
        "canal": "GaliciaTV.ar",
        "evento": "Telexornal mediodía - Fin de semana",
        "hora_inicio": "09:25",
        "hora_fin": "10:06",
        "progreso": 16
    },
    {
        "canal": "Glitz.ar",
        "evento": "No Data",
        "hora_inicio": "09:00",
        "hora_fin": "10:00",
        "progreso": 52
    },
    {
        "canal": "Golden.ar",
        "evento": "Mamma mía",
        "hora_inicio": "08:54",
        "hora_fin": "10:53",
        "progreso": 31
    },
    {
        "canal": "GoldenEdge.ar",
        "evento": "Almas gemelas",
        "hora_inicio": "07:56",
        "hora_fin": "09:43",
        "progreso": 89
    },
    {
        "canal": "GolfChannel.ar",
        "evento": "Round 2",
        "hora_inicio": "08:00",
        "hora_fin": "13:00",
        "progreso": 30
    },
    {
        "canal": "GolTV.ar",
        "evento": "No Data",
        "hora_inicio": "09:00",
        "hora_fin": "10:00",
        "progreso": 52
    },
    {
        "canal": "HAPSATV.ar",
        "evento": "Turf en vivo - Palermo, San Isidro y La Plata",
        "hora_inicio": "08:00",
        "hora_fin": "12:00",
        "progreso": 38
    },
    {
        "canal": "HBO.ar",
        "evento": "El gato con botas",
        "hora_inicio": "08:26",
        "hora_fin": "10:01",
        "progreso": 69
    },
    {
        "canal": "HBO2.ar",
        "evento": "La posesión de la momia",
        "hora_inicio": "08:55",
        "hora_fin": "11:10",
        "progreso": 27
    },
    {
        "canal": "HBOFamily.ar",
        "evento": "LEGO Ninjago: La película",
        "hora_inicio": "09:00",
        "hora_fin": "10:43",
        "progreso": 30
    },
    {
        "canal": "HBOMundi.ar",
        "evento": "El brutalista",
        "hora_inicio": "08:46",
        "hora_fin": "12:10",
        "progreso": 22
    },
    {
        "canal": "HBOOeste.ar",
        "evento": "Harry Potter y el misterio del príncipe",
        "hora_inicio": "09:00",
        "hora_fin": "11:40",
        "progreso": 19
    },
    {
        "canal": "HBOPlus(Panamericano).ar",
        "evento": "Venom",
        "hora_inicio": "08:30",
        "hora_fin": "10:30",
        "progreso": 51
    },
    {
        "canal": "HBOPlusEste.ar",
        "evento": "Venom",
        "hora_inicio": "08:30",
        "hora_fin": "10:30",
        "progreso": 51
    },
    {
        "canal": "HBOPlusPanregional.ar",
        "evento": "No Data",
        "hora_inicio": "09:00",
        "hora_fin": "10:00",
        "progreso": 52
    },
    {
        "canal": "HBOPop.ar",
        "evento": "Un papá genial",
        "hora_inicio": "09:00",
        "hora_fin": "10:35",
        "progreso": 33
    },
    {
        "canal": "HBOSignature.ar",
        "evento": "Donyale Luna: Supermodelo",
        "hora_inicio": "07:49",
        "hora_fin": "09:32",
        "progreso": 99
    },
    {
        "canal": "HBOXtreme(Oeste).ar",
        "evento": "No Data",
        "hora_inicio": "09:00",
        "hora_fin": "10:00",
        "progreso": 52
    },
    {
        "canal": "HBOXtreme(Panamericano).ar",
        "evento": "El plan perfecto",
        "hora_inicio": "09:13",
        "hora_fin": "11:24",
        "progreso": 14
    },
    {
        "canal": "HBOXtreme(Panregional).ar",
        "evento": "No Data",
        "hora_inicio": "09:00",
        "hora_fin": "10:00",
        "progreso": 52
    },
    {
        "canal": "HBOXtreme.ar",
        "evento": "El plan perfecto",
        "hora_inicio": "09:13",
        "hora_fin": "11:24",
        "progreso": 14
    },
    {
        "canal": "HGTV.ar",
        "evento": "Nuestro hogar en la montaña",
        "hora_inicio": "09:29",
        "hora_fin": "09:52",
        "progreso": 11
    },
    {
        "canal": "HispanTV.ar",
        "evento": "HispanTV noticias",
        "hora_inicio": "09:30",
        "hora_fin": "10:00",
        "progreso": 5
    },
    {
        "canal": "History.ar",
        "evento": "Infomerciales",
        "hora_inicio": "09:00",
        "hora_fin": "10:00",
        "progreso": 52
    },
    {
        "canal": "History2.ar",
        "evento": "Gigantes de la industria",
        "hora_inicio": "08:50",
        "hora_fin": "10:30",
        "progreso": 41
    },
    {
        "canal": "HolaTV.ar",
        "evento": "Sí quiero",
        "hora_inicio": "09:00",
        "hora_fin": "10:00",
        "progreso": 52
    },
    {
        "canal": "HTV.ar",
        "evento": "HTV",
        "hora_inicio": "09:00",
        "hora_fin": "14:00",
        "progreso": 10
    },
    {
        "canal": "I-SAT.ar",
        "evento": "No Data",
        "hora_inicio": "09:00",
        "hora_fin": "10:00",
        "progreso": 52
    },
    {
        "canal": "InvestigationDiscovery.ar",
        "evento": "Cuando el mal se disfraza",
        "hora_inicio": "09:00",
        "hora_fin": "09:45",
        "progreso": 70
    },
    {
        "canal": "IVC.ar",
        "evento": "No Data",
        "hora_inicio": "09:00",
        "hora_fin": "10:00",
        "progreso": 52
    },
    {
        "canal": "KZO.ar",
        "evento": "No Data",
        "hora_inicio": "09:00",
        "hora_fin": "10:00",
        "progreso": 52
    },
    {
        "canal": "LasEstrellas.ar",
        "evento": "Seguiré tus pasos",
        "hora_inicio": "09:05",
        "hora_fin": "10:50",
        "progreso": 25
    },
    {
        "canal": "Lifetime.ar",
        "evento": "No Data",
        "hora_inicio": "09:00",
        "hora_fin": "10:00",
        "progreso": 52
    },
    {
        "canal": "LN+.ar",
        "evento": "Miralo bien",
        "hora_inicio": "09:00",
        "hora_fin": "13:00",
        "progreso": 13
    },
    {
        "canal": "MasChic.ar",
        "evento": "Planet Action",
        "hora_inicio": "09:30",
        "hora_fin": "10:00",
        "progreso": 5
    },
    {
        "canal": "Metro.ar",
        "evento": "Revolución en valores",
        "hora_inicio": "09:30",
        "hora_fin": "10:00",
        "progreso": 5
    },
    {
        "canal": "MTV.ar",
        "evento": "Ridiculousness",
        "hora_inicio": "09:20",
        "hora_fin": "09:45",
        "progreso": 46
    },
    {
        "canal": "MTVHits.ar",
        "evento": "No Data",
        "hora_inicio": "09:00",
        "hora_fin": "10:00",
        "progreso": 52
    },
    {
        "canal": "MuchMusic.ar",
        "evento": "No Data",
        "hora_inicio": "09:00",
        "hora_fin": "10:00",
        "progreso": 52
    },
    {
        "canal": "Musictop.ar",
        "evento": "MusicTop",
        "hora_inicio": "09:00",
        "hora_fin": "10:00",
        "progreso": 52
    },
    {
        "canal": "NatGeoKids.ar",
        "evento": "No Data",
        "hora_inicio": "09:00",
        "hora_fin": "10:00",
        "progreso": 52
    },
    {
        "canal": "NationalGeographic.ar",
        "evento": "Ciudades perdidas con Albert Lin",
        "hora_inicio": "09:03",
        "hora_fin": "10:04",
        "progreso": 46
    },
    {
        "canal": "NationalGeographicWild.ar",
        "evento": "No Data",
        "hora_inicio": "09:00",
        "hora_fin": "10:00",
        "progreso": 52
    },
    {
        "canal": "NBATV.ar",
        "evento": "WNBA Shot Clock: Games of the Night",
        "hora_inicio": "09:30",
        "hora_fin": "10:00",
        "progreso": 5
    },
    {
        "canal": "NetTV.ar",
        "evento": "Caras y negocios",
        "hora_inicio": "09:30",
        "hora_fin": "10:30",
        "progreso": 2
    },
    {
        "canal": "Nick2.ar",
        "evento": "No Data",
        "hora_inicio": "09:00",
        "hora_fin": "10:00",
        "progreso": 52
    },
    {
        "canal": "NickJr..ar",
        "evento": "Blaze y los Monster Machines",
        "hora_inicio": "09:20",
        "hora_fin": "09:45",
        "progreso": 46
    },
    {
        "canal": "NickToons.ar",
        "evento": "No Data",
        "hora_inicio": "09:00",
        "hora_fin": "10:00",
        "progreso": 52
    },
    {
        "canal": "Pakapaka.ar",
        "evento": "Amigos",
        "hora_inicio": "09:15",
        "hora_fin": "09:45",
        "progreso": 55
    },
    {
        "canal": "ParamountNetwork.ar",
        "evento": "No Data",
        "hora_inicio": "09:00",
        "hora_fin": "10:00",
        "progreso": 52
    },
    {
        "canal": "Pasiones.ar",
        "evento": "Pantanal",
        "hora_inicio": "09:00",
        "hora_fin": "10:00",
        "progreso": 52
    },
    {
        "canal": "PenthouseGold.ar",
        "evento": "1 club de chicas asesinas",
        "hora_inicio": "09:20",
        "hora_fin": "10:42",
        "progreso": 14
    },
    {
        "canal": "Playboy.ar",
        "evento": "Neighborhood Rumors",
        "hora_inicio": "09:31",
        "hora_fin": "09:55",
        "progreso": 2
    },
    {
        "canal": "Quiero.ar",
        "evento": "Media hora con...",
        "hora_inicio": "09:30",
        "hora_fin": "10:00",
        "progreso": 5
    },
    {
        "canal": "RaiItalia.ar",
        "evento": "O anche no Estate",
        "hora_inicio": "09:15",
        "hora_fin": "10:00",
        "progreso": 36
    },
    {
        "canal": "RussiaToday.ar",
        "evento": "Entrevista mix",
        "hora_inicio": "09:30",
        "hora_fin": "10:00",
        "progreso": 5
    },
    {
        "canal": "SmithsonianChannel.ar",
        "evento": "No Data",
        "hora_inicio": "09:00",
        "hora_fin": "10:00",
        "progreso": 52
    },
    {
        "canal": "Sony.ar",
        "evento": "TeveCompras",
        "hora_inicio": "09:30",
        "hora_fin": "10:00",
        "progreso": 5
    },
    {
        "canal": "Space.ar",
        "evento": "Mad Max",
        "hora_inicio": "08:28",
        "hora_fin": "10:04",
        "progreso": 66
    },
    {
        "canal": "StarAction(Oeste).ar",
        "evento": "No Data",
        "hora_inicio": "09:00",
        "hora_fin": "10:00",
        "progreso": 52
    },
    {
        "canal": "StarAction.ar",
        "evento": "No Data",
        "hora_inicio": "09:00",
        "hora_fin": "10:00",
        "progreso": 52
    },
    {
        "canal": "StarChannel.ar",
        "evento": "Misión Babilonia",
        "hora_inicio": "07:51",
        "hora_fin": "10:00",
        "progreso": 78
    },
    {
        "canal": "StarCinema.ar",
        "evento": "No Data",
        "hora_inicio": "09:00",
        "hora_fin": "10:00",
        "progreso": 52
    },
    {
        "canal": "StarClassics.ar",
        "evento": "No Data",
        "hora_inicio": "09:00",
        "hora_fin": "10:00",
        "progreso": 52
    },
    {
        "canal": "StarComedy.ar",
        "evento": "No Data",
        "hora_inicio": "09:00",
        "hora_fin": "10:00",
        "progreso": 52
    },
    {
        "canal": "StarFun(Oeste).ar",
        "evento": "No Data",
        "hora_inicio": "09:00",
        "hora_fin": "10:00",
        "progreso": 52
    },
    {
        "canal": "StarFun.ar",
        "evento": "No Data",
        "hora_inicio": "09:00",
        "hora_fin": "10:00",
        "progreso": 52
    },
    {
        "canal": "StarHits.ar",
        "evento": "No Data",
        "hora_inicio": "09:00",
        "hora_fin": "10:00",
        "progreso": 52
    },
    {
        "canal": "StarLife.ar",
        "evento": "No Data",
        "hora_inicio": "09:00",
        "hora_fin": "10:00",
        "progreso": 52
    },
    {
        "canal": "StarSeries(Oeste).ar",
        "evento": "No Data",
        "hora_inicio": "09:00",
        "hora_fin": "10:00",
        "progreso": 52
    },
    {
        "canal": "StarSeries.ar",
        "evento": "No Data",
        "hora_inicio": "09:00",
        "hora_fin": "10:00",
        "progreso": 52
    },
    {
        "canal": "StudioUniversal.ar",
        "evento": "Misterio en Mistletoe Lane",
        "hora_inicio": "08:00",
        "hora_fin": "09:45",
        "progreso": 87
    },
    {
        "canal": "Syfy.ar",
        "evento": "No Data",
        "hora_inicio": "09:00",
        "hora_fin": "10:00",
        "progreso": 52
    },
    {
        "canal": "TaTeTi.ar",
        "evento": "No Data",
        "hora_inicio": "09:00",
        "hora_fin": "10:00",
        "progreso": 52
    },
    {
        "canal": "TBS.ar",
        "evento": "No Data",
        "hora_inicio": "09:00",
        "hora_fin": "10:00",
        "progreso": 52
    },
    {
        "canal": "TCM.ar",
        "evento": "Quo vadis",
        "hora_inicio": "08:03",
        "hora_fin": "11:06",
        "progreso": 48
    },
    {
        "canal": "TECtv.ar",
        "evento": "TecTV",
        "hora_inicio": "08:00",
        "hora_fin": "12:00",
        "progreso": 38
    },
    {
        "canal": "Telediario.ar",
        "evento": "Resumen de noticias",
        "hora_inicio": "07:00",
        "hora_fin": "13:00",
        "progreso": 42
    },
    {
        "canal": "Telefe.ar",
        "evento": "El Chavo y el Chapulín colorado",
        "hora_inicio": "09:15",
        "hora_fin": "11:00",
        "progreso": 15
    },
    {
        "canal": "TelefeCordoba.ar",
        "evento": "Disney Jr.",
        "hora_inicio": "09:00",
        "hora_fin": "10:00",
        "progreso": 52
    },
    {
        "canal": "TelefeRosario.ar",
        "evento": "Disney Jr.",
        "hora_inicio": "09:30",
        "hora_fin": "10:30",
        "progreso": 2
    },
    {
        "canal": "TelefeSantaFe.ar",
        "evento": "Fin de transmisión",
        "hora_inicio": "06:00",
        "hora_fin": "10:30",
        "progreso": 78
    },
    {
        "canal": "Telehit.ar",
        "evento": "Daebak K-pop",
        "hora_inicio": "09:30",
        "hora_fin": "10:30",
        "progreso": 2
    },
    {
        "canal": "Telemax.ar",
        "evento": "Tiempo de viajar",
        "hora_inicio": "09:30",
        "hora_fin": "10:00",
        "progreso": 5
    },
    {
        "canal": "TelemundoInternacional.ar",
        "evento": "No Data",
        "hora_inicio": "09:00",
        "hora_fin": "10:00",
        "progreso": 52
    },
    {
        "canal": "teleSUR.ar",
        "evento": "Telesur Noticias",
        "hora_inicio": "09:30",
        "hora_fin": "10:00",
        "progreso": 5
    },
    {
        "canal": "TelevisionPublica.ar",
        "evento": "Aire de campo",
        "hora_inicio": "09:00",
        "hora_fin": "10:00",
        "progreso": 52
    },
    {
        "canal": "TierraMiaTV.ar",
        "evento": "TierraMia TV",
        "hora_inicio": "09:00",
        "hora_fin": "10:00",
        "progreso": 52
    },
    {
        "canal": "TLC.ar",
        "evento": "A confirmar",
        "hora_inicio": "09:30",
        "hora_fin": "10:00",
        "progreso": 5
    },
    {
        "canal": "TLNovelas.ar",
        "evento": "Rosa salvaje",
        "hora_inicio": "08:10",
        "hora_fin": "11:10",
        "progreso": 45
    },
    {
        "canal": "TN.ar",
        "evento": "TN Fin de semana",
        "hora_inicio": "07:00",
        "hora_fin": "13:00",
        "progreso": 42
    },
    {
        "canal": "TNT.ar",
        "evento": "El último gran héroe",
        "hora_inicio": "07:47",
        "hora_fin": "10:03",
        "progreso": 76
    },
    {
        "canal": "TNTSeries.ar",
        "evento": "La ley y el orden: UVE",
        "hora_inicio": "09:14",
        "hora_fin": "10:06",
        "progreso": 33
    },
    {
        "canal": "Tooncast.ar",
        "evento": "Mike, Lu y Og",
        "hora_inicio": "09:31",
        "hora_fin": "09:42",
        "progreso": 5
    },
    {
        "canal": "TruTV.ar",
        "evento": "No Data",
        "hora_inicio": "09:00",
        "hora_fin": "10:00",
        "progreso": 52
    },
    {
        "canal": "TurismoVisionArgentina.ar",
        "evento": "Turismo Visión Argentina",
        "hora_inicio": "09:00",
        "hora_fin": "12:00",
        "progreso": 17
    },
    {
        "canal": "TV5.ar",
        "evento": "Etapa 14: mulhouse / Le markstein fellering",
        "hora_inicio": "09:31",
        "hora_fin": "12:46",
        "progreso": 0
    },
    {
        "canal": "TVCiudad.ar",
        "evento": "Paseo animado",
        "hora_inicio": "09:00",
        "hora_fin": "11:00",
        "progreso": 26
    },
    {
        "canal": "TVCortos.ar",
        "evento": "No Data",
        "hora_inicio": "09:00",
        "hora_fin": "10:00",
        "progreso": 52
    },
    {
        "canal": "TVE.ar",
        "evento": "Tenderete",
        "hora_inicio": "08:20",
        "hora_fin": "09:55",
        "progreso": 75
    },
    {
        "canal": "TVGlobo.ar",
        "evento": "É de casa",
        "hora_inicio": "08:30",
        "hora_fin": "11:45",
        "progreso": 31
    },
    {
        "canal": "TVNacionalUruguay.ar",
        "evento": "Baby deportivo",
        "hora_inicio": "09:30",
        "hora_fin": "10:30",
        "progreso": 2
    },
    {
        "canal": "TVNCHILE.ar",
        "evento": "Aires de Chile",
        "hora_inicio": "09:30",
        "hora_fin": "10:00",
        "progreso": 5
    },
    {
        "canal": "TVPublica.ar",
        "evento": "Aire de campo",
        "hora_inicio": "09:00",
        "hora_fin": "10:00",
        "progreso": 52
    },
    {
        "canal": "TyCSports.ar",
        "evento": "La cobertura de Argentina y la previa de Francia vs. Inglaterra",
        "hora_inicio": "09:00",
        "hora_fin": "10:30",
        "progreso": 35
    },
    {
        "canal": "TyCSports2.ar",
        "evento": "TyC Sports 2",
        "hora_inicio": "00:00",
        "hora_fin": "12:00",
        "progreso": 79
    },
    {
        "canal": "UniversalTV.ar",
        "evento": "Chicago Med",
        "hora_inicio": "09:20",
        "hora_fin": "10:10",
        "progreso": 23
    },
    {
        "canal": "UruguayNaturalTV.ar",
        "evento": "Uruguay Natural TV",
        "hora_inicio": "08:00",
        "hora_fin": "12:00",
        "progreso": 38
    },
    {
        "canal": "Venus.ar",
        "evento": "I Confess - Vol. 1 - Parte 1",
        "hora_inicio": "08:59",
        "hora_fin": "10:35",
        "progreso": 34
    },
    {
        "canal": "VH1.ar",
        "evento": "No Data",
        "hora_inicio": "09:00",
        "hora_fin": "10:00",
        "progreso": 52
    },
    {
        "canal": "VH1MegaHits.ar",
        "evento": "No Data",
        "hora_inicio": "09:00",
        "hora_fin": "10:00",
        "progreso": 52
    },
    {
        "canal": "Viajar.ar",
        "evento": "No Data",
        "hora_inicio": "09:00",
        "hora_fin": "10:00",
        "progreso": 52
    },
    {
        "canal": "Volver.ar",
        "evento": "El picnic de los Campanelli",
        "hora_inicio": "08:40",
        "hora_fin": "10:00",
        "progreso": 64
    },
    {
        "canal": "VTV.ar",
        "evento": "Ferias y mercados",
        "hora_inicio": "09:00",
        "hora_fin": "10:00",
        "progreso": 52
    },
    {
        "canal": "WarnerChannel.ar",
        "evento": "10.000 AC",
        "hora_inicio": "08:43",
        "hora_fin": "10:36",
        "progreso": 43
    },
    {
        "canal": "ZooMoo.ar",
        "evento": "Las aventuras de Miss Spider",
        "hora_inicio": "09:30",
        "hora_fin": "10:00",
        "progreso": 5
    }
]