[
    {
        "canal": "24/7CanaldeNoticias.ar",
        "evento": "Contenido variado",
        "hora_inicio": "13:00",
        "hora_fin": "20:00",
        "progreso": 66
    },
    {
        "canal": "A24.ar",
        "evento": "El diario de la tarde",
        "hora_inicio": "16:00",
        "hora_fin": "19:00",
        "progreso": 54
    },
    {
        "canal": "AMC.ar",
        "evento": "RoboCop",
        "hora_inicio": "15:40",
        "hora_fin": "17:50",
        "progreso": 91
    },
    {
        "canal": "AmericaSports.ar",
        "evento": "Turismo y cultura",
        "hora_inicio": "17:30",
        "hora_fin": "18:00",
        "progreso": 28
    },
    {
        "canal": "AmericaTV.ar",
        "evento": "Pasión de sábado",
        "hora_inicio": "13:00",
        "hora_fin": "19:50",
        "progreso": 67
    },
    {
        "canal": "AnimalPlanet.ar",
        "evento": "Los Irwin",
        "hora_inicio": "17:25",
        "hora_fin": "18:21",
        "progreso": 23
    },
    {
        "canal": "ArgentinisimaSatelital.ar",
        "evento": "Argentinisima satelital",
        "hora_inicio": "15:00",
        "hora_fin": "18:00",
        "progreso": 88
    },
    {
        "canal": "Atreseries.ar",
        "evento": "Rock Story",
        "hora_inicio": "16:48",
        "hora_fin": "17:40",
        "progreso": 96
    },
    {
        "canal": "AXN.ar",
        "evento": "NCIS",
        "hora_inicio": "17:25",
        "hora_fin": "18:25",
        "progreso": 22
    },
    {
        "canal": "BabyTV.ar",
        "evento": "Descubriendo con Vegibugs",
        "hora_inicio": "17:30",
        "hora_fin": "18:00",
        "progreso": 28
    },
    {
        "canal": "Bloomberg.ar",
        "evento": "VivaTech x Bloomberg Awards",
        "hora_inicio": "17:30",
        "hora_fin": "18:00",
        "progreso": 28
    },
    {
        "canal": "C5N.ar",
        "evento": "La voz de la calle",
        "hora_inicio": "14:30",
        "hora_fin": "18:00",
        "progreso": 89
    },
    {
        "canal": "Canal21.ar",
        "evento": "Audiencia general",
        "hora_inicio": "17:00",
        "hora_fin": "18:00",
        "progreso": 64
    },
    {
        "canal": "Canal26.ar",
        "evento": "La tarde del finde",
        "hora_inicio": "16:30",
        "hora_fin": "19:00",
        "progreso": 45
    },
    {
        "canal": "CanalDeLaCiudad.ar",
        "evento": "Pantagruélicos famosos",
        "hora_inicio": "17:00",
        "hora_fin": "18:00",
        "progreso": 64
    },
    {
        "canal": "CanalDeLaMusica.ar",
        "evento": "CM rock",
        "hora_inicio": "17:00",
        "hora_fin": "18:00",
        "progreso": 64
    },
    {
        "canal": "CanalRural.ar",
        "evento": "Aromas del Terruño",
        "hora_inicio": "17:30",
        "hora_fin": "18:00",
        "progreso": 28
    },
    {
        "canal": "CartoonNetwork.ar",
        "evento": "Spider-Man: Un nuevo universo",
        "hora_inicio": "16:01",
        "hora_fin": "17:58",
        "progreso": 83
    },
    {
        "canal": "CineAr.ar",
        "evento": "El negoción",
        "hora_inicio": "16:00",
        "hora_fin": "18:00",
        "progreso": 82
    },
    {
        "canal": "Cinecanal.ar",
        "evento": "Emma",
        "hora_inicio": "17:12",
        "hora_fin": "19:46",
        "progreso": 17
    },
    {
        "canal": "Cinelatino.ar",
        "evento": "Asesino de traileros",
        "hora_inicio": "17:00",
        "hora_fin": "18:35",
        "progreso": 40
    },
    {
        "canal": "Cinemax(Sur).ar",
        "evento": "La momia",
        "hora_inicio": "17:28",
        "hora_fin": "19:45",
        "progreso": 7
    },
    {
        "canal": "Cinemax.ar",
        "evento": "Rápidos y furiosos 7",
        "hora_inicio": "17:13",
        "hora_fin": "19:36",
        "progreso": 17
    },
    {
        "canal": "CiudadMagazine.ar",
        "evento": "El maestro del dinero",
        "hora_inicio": "17:00",
        "hora_fin": "18:45",
        "progreso": 36
    },
    {
        "canal": "CN23.ar",
        "evento": "CN 23",
        "hora_inicio": "17:00",
        "hora_fin": "18:00",
        "progreso": 64
    },
    {
        "canal": "CNN.ar",
        "evento": "The Fourth in America: Celebrating 250",
        "hora_inicio": "13:00",
        "hora_fin": "19:30",
        "progreso": 71
    },
    {
        "canal": "CNNenEspanol.ar",
        "evento": "Deportes CNN",
        "hora_inicio": "17:00",
        "hora_fin": "18:00",
        "progreso": 64
    },
    {
        "canal": "ComedyCentral.ar",
        "evento": "Frasier",
        "hora_inicio": "17:35",
        "hora_fin": "18:00",
        "progreso": 13
    },
    {
        "canal": "ConexionEducativa.ar",
        "evento": "Conexión educativa",
        "hora_inicio": "15:00",
        "hora_fin": "18:00",
        "progreso": 88
    },
    {
        "canal": "ConstruirTV.ar",
        "evento": "Diseño para habitar",
        "hora_inicio": "17:00",
        "hora_fin": "18:30",
        "progreso": 42
    },
    {
        "canal": "CronicaTV.ar",
        "evento": "El runrún del espectáculo",
        "hora_inicio": "16:00",
        "hora_fin": "18:00",
        "progreso": 82
    },
    {
        "canal": "Discovery.ar",
        "evento": "Supervivencia al desnudo: edición extrema",
        "hora_inicio": "16:41",
        "hora_fin": "18:14",
        "progreso": 61
    },
    {
        "canal": "DiscoveryChannel.ar",
        "evento": "Supervivencia al desnudo: edición extrema",
        "hora_inicio": "16:41",
        "hora_fin": "18:14",
        "progreso": 61
    },
    {
        "canal": "DiscoveryHomeAndHealth.ar",
        "evento": "Campeonato de reposteros: delicias de primavera",
        "hora_inicio": "17:09",
        "hora_fin": "17:57",
        "progreso": 61
    },
    {
        "canal": "DiscoveryKids.ar",
        "evento": "Lupi y Baduki",
        "hora_inicio": "17:34",
        "hora_fin": "17:45",
        "progreso": 40
    },
    {
        "canal": "DiscoveryTurbo.ar",
        "evento": "Invasión de garajes",
        "hora_inicio": "17:36",
        "hora_fin": "18:30",
        "progreso": 4
    },
    {
        "canal": "DisneyChannel.ar",
        "evento": "Los hechiceros más allá de Waverly Place",
        "hora_inicio": "17:29",
        "hora_fin": "17:59",
        "progreso": 31
    },
    {
        "canal": "DisneyJunior.ar",
        "evento": "Princesita Sofía",
        "hora_inicio": "17:30",
        "hora_fin": "18:00",
        "progreso": 28
    },
    {
        "canal": "ElGarageTv.ar",
        "evento": "Tu tren",
        "hora_inicio": "17:30",
        "hora_fin": "18:00",
        "progreso": 28
    },
    {
        "canal": "ElGourmet.ar",
        "evento": "Maestros del alfajor",
        "hora_inicio": "17:30",
        "hora_fin": "18:00",
        "progreso": 28
    },
    {
        "canal": "ELNueve.ar",
        "evento": "Nara que ver",
        "hora_inicio": "17:00",
        "hora_fin": "18:00",
        "progreso": 64
    },
    {
        "canal": "ELTrece.ar",
        "evento": "La familia Ingalls",
        "hora_inicio": "11:00",
        "hora_fin": "18:00",
        "progreso": 94
    },
    {
        "canal": "Encuentro.ar",
        "evento": "Atlántico Sur",
        "hora_inicio": "17:00",
        "hora_fin": "18:00",
        "progreso": 64
    },
    {
        "canal": "ESPN.ar",
        "evento": "ESPN Mundial",
        "hora_inicio": "17:00",
        "hora_fin": "20:00",
        "progreso": 21
    },
    {
        "canal": "ESPN2.ar",
        "evento": "A confirmar",
        "hora_inicio": "15:00",
        "hora_fin": "18:10",
        "progreso": 83
    },
    {
        "canal": "ESPN3.ar",
        "evento": "A confirmar",
        "hora_inicio": "15:00",
        "hora_fin": "18:00",
        "progreso": 88
    },
    {
        "canal": "ESPN4.ar",
        "evento": "Tercera ronda, Broadmoor Golf Club, Colorado Springs, CO, USA",
        "hora_inicio": "13:00",
        "hora_fin": "18:00",
        "progreso": 92
    },
    {
        "canal": "ESPNExtra.ar",
        "evento": "USGA US Senior Open Golf Championship",
        "hora_inicio": "17:00",
        "hora_fin": "18:00",
        "progreso": 64
    },
    {
        "canal": "ESPNSur.ar",
        "evento": "ESPN Mundial",
        "hora_inicio": "16:00",
        "hora_fin": "18:00",
        "progreso": 82
    },
    {
        "canal": "ESPNSur2.ar",
        "evento": "ESPN 2 Argentina",
        "hora_inicio": "16:00",
        "hora_fin": "19:00",
        "progreso": 54
    },
    {
        "canal": "ESPNSur3.ar",
        "evento": "ESPN 3 Sur",
        "hora_inicio": "16:00",
        "hora_fin": "19:00",
        "progreso": 54
    },
    {
        "canal": "ESPNSur4.ar",
        "evento": "U.S. Senior Open Championship 2026",
        "hora_inicio": "14:00",
        "hora_fin": "19:00",
        "progreso": 72
    },
    {
        "canal": "EuropaEuropa.ar",
        "evento": "El segundo trágico Fantozzi",
        "hora_inicio": "16:20",
        "hora_fin": "18:25",
        "progreso": 62
    },
    {
        "canal": "EWTN.ar",
        "evento": "La misericordia y el perdón",
        "hora_inicio": "17:30",
        "hora_fin": "18:00",
        "progreso": 28
    },
    {
        "canal": "filmAndarts.ar",
        "evento": "Macbeth",
        "hora_inicio": "15:55",
        "hora_fin": "18:30",
        "progreso": 66
    },
    {
        "canal": "FOX Sports",
        "evento": "Gran Premio de Gran Bretaña, Silverstone",
        "hora_inicio": "17:05",
        "hora_fin": "18:25",
        "progreso": 41
    },
    {
        "canal": "FOXSports2.ar",
        "evento": "Moving",
        "hora_inicio": "17:00",
        "hora_fin": "18:00",
        "progreso": 64
    },
    {
        "canal": "FOXSports3.ar",
        "evento": "Copenhagen, Denmark",
        "hora_inicio": "16:00",
        "hora_fin": "18:00",
        "progreso": 82
    },
    {
        "canal": "FOXSportsConoSur.ar",
        "evento": "Gran Premio de Gran Bretaña, Silverstone",
        "hora_inicio": "17:05",
        "hora_fin": "18:25",
        "progreso": 41
    },
    {
        "canal": "France24enEspanol.ar",
        "evento": "Noticias",
        "hora_inicio": "17:30",
        "hora_fin": "17:45",
        "progreso": 56
    },
    {
        "canal": "FX.ar",
        "evento": "Apolo 11",
        "hora_inicio": "15:46",
        "hora_fin": "17:44",
        "progreso": 95
    },
    {
        "canal": "GaliciaTV.ar",
        "evento": "O tempo",
        "hora_inicio": "16:50",
        "hora_fin": "20:30",
        "progreso": 22
    },
    {
        "canal": "Golden.ar",
        "evento": "Los juegos del hambre: En llamas",
        "hora_inicio": "16:39",
        "hora_fin": "19:14",
        "progreso": 38
    },
    {
        "canal": "GoldenEdge.ar",
        "evento": "El vengador",
        "hora_inicio": "16:13",
        "hora_fin": "18:09",
        "progreso": 73
    },
    {
        "canal": "GolfChannel.ar",
        "evento": "Round 3",
        "hora_inicio": "14:00",
        "hora_fin": "19:00",
        "progreso": 72
    },
    {
        "canal": "HAPSATV.ar",
        "evento": "Turf en vivo - Palermo, San Isidro y La Plata",
        "hora_inicio": "16:00",
        "hora_fin": "20:00",
        "progreso": 41
    },
    {
        "canal": "HBO.ar",
        "evento": "Escape bajo fuego",
        "hora_inicio": "15:55",
        "hora_fin": "17:58",
        "progreso": 84
    },
    {
        "canal": "HBO2.ar",
        "evento": "Al filo del mañana",
        "hora_inicio": "15:50",
        "hora_fin": "17:49",
        "progreso": 91
    },
    {
        "canal": "HBOFamily.ar",
        "evento": "Luna de miel en familia",
        "hora_inicio": "16:49",
        "hora_fin": "18:49",
        "progreso": 41
    },
    {
        "canal": "HBOMundi.ar",
        "evento": "ET, el extraterrestre",
        "hora_inicio": "17:00",
        "hora_fin": "19:00",
        "progreso": 32
    },
    {
        "canal": "HBOOeste.ar",
        "evento": "Everest",
        "hora_inicio": "16:42",
        "hora_fin": "18:50",
        "progreso": 44
    },
    {
        "canal": "HBOPlus(Panamericano).ar",
        "evento": "Jurassic Park",
        "hora_inicio": "15:50",
        "hora_fin": "18:00",
        "progreso": 83
    },
    {
        "canal": "HBOPlusEste.ar",
        "evento": "Jurassic Park",
        "hora_inicio": "15:50",
        "hora_fin": "18:00",
        "progreso": 83
    },
    {
        "canal": "HBOPop.ar",
        "evento": "Comer, rezar, amar",
        "hora_inicio": "15:23",
        "hora_fin": "17:50",
        "progreso": 92
    },
    {
        "canal": "HBOSignature.ar",
        "evento": "True Detective",
        "hora_inicio": "17:11",
        "hora_fin": "18:18",
        "progreso": 40
    },
    {
        "canal": "HBOXtreme(Panamericano).ar",
        "evento": "Matrix resurrecciones",
        "hora_inicio": "17:20",
        "hora_fin": "19:53",
        "progreso": 12
    },
    {
        "canal": "HBOXtreme.ar",
        "evento": "Matrix resurrecciones",
        "hora_inicio": "17:20",
        "hora_fin": "19:53",
        "progreso": 12
    },
    {
        "canal": "HGTV.ar",
        "evento": "¿Qué le pasa a esa casa?",
        "hora_inicio": "17:17",
        "hora_fin": "18:04",
        "progreso": 45
    },
    {
        "canal": "HispanTV.ar",
        "evento": "Mujeres de resistencia",
        "hora_inicio": "17:30",
        "hora_fin": "18:00",
        "progreso": 28
    },
    {
        "canal": "History.ar",
        "evento": "101 objetos que cambiaron al mundo",
        "hora_inicio": "16:54",
        "hora_fin": "18:32",
        "progreso": 45
    },
    {
        "canal": "History2.ar",
        "evento": "Inventos legendarios",
        "hora_inicio": "17:08",
        "hora_fin": "17:54",
        "progreso": 66
    },
    {
        "canal": "HolaTV.ar",
        "evento": "Cóctel de noticias",
        "hora_inicio": "17:30",
        "hora_fin": "18:00",
        "progreso": 28
    },
    {
        "canal": "HTV.ar",
        "evento": "HTV",
        "hora_inicio": "14:00",
        "hora_fin": "01:00",
        "progreso": 33
    },
    {
        "canal": "InvestigationDiscovery.ar",
        "evento": "Asesinatos en Silicon Valley",
        "hora_inicio": "17:18",
        "hora_fin": "18:04",
        "progreso": 44
    },
    {
        "canal": "LasEstrellas.ar",
        "evento": "Hotel todo incluido",
        "hora_inicio": "16:25",
        "hora_fin": "21:50",
        "progreso": 22
    },
    {
        "canal": "LN+.ar",
        "evento": "+Noticias sábado",
        "hora_inicio": "16:00",
        "hora_fin": "20:00",
        "progreso": 41
    },
    {
        "canal": "MasChic.ar",
        "evento": "TURN: espías de Washington",
        "hora_inicio": "17:20",
        "hora_fin": "18:10",
        "progreso": 36
    },
    {
        "canal": "Metro.ar",
        "evento": "Mercado por expertos",
        "hora_inicio": "17:30",
        "hora_fin": "18:00",
        "progreso": 28
    },
    {
        "canal": "MTV.ar",
        "evento": "¿Por qué me escondes?",
        "hora_inicio": "17:05",
        "hora_fin": "17:50",
        "progreso": 74
    },
    {
        "canal": "Musictop.ar",
        "evento": "MusicTop",
        "hora_inicio": "17:00",
        "hora_fin": "18:00",
        "progreso": 64
    },
    {
        "canal": "NationalGeographic.ar",
        "evento": "Tesoros perdidos de Roma",
        "hora_inicio": "16:57",
        "hora_fin": "17:59",
        "progreso": 66
    },
    {
        "canal": "NBATV.ar",
        "evento": "Milwaukee vs. Warriors Blue",
        "hora_inicio": "16:00",
        "hora_fin": "18:00",
        "progreso": 82
    },
    {
        "canal": "NetTV.ar",
        "evento": "Net TV",
        "hora_inicio": "16:00",
        "hora_fin": "19:00",
        "progreso": 54
    },
    {
        "canal": "NickJr..ar",
        "evento": "Tim Rex en el espacio",
        "hora_inicio": "17:30",
        "hora_fin": "17:40",
        "progreso": 84
    },
    {
        "canal": "Pakapaka.ar",
        "evento": "Inteligencia animal",
        "hora_inicio": "17:30",
        "hora_fin": "17:45",
        "progreso": 56
    },
    {
        "canal": "Pasiones.ar",
        "evento": "Tres hermanas",
        "hora_inicio": "17:00",
        "hora_fin": "18:00",
        "progreso": 64
    },
    {
        "canal": "PenthouseGold.ar",
        "evento": "Analiza mi conchita húmeda",
        "hora_inicio": "16:57",
        "hora_fin": "18:43",
        "progreso": 39
    },
    {
        "canal": "Playboy.ar",
        "evento": "Secretos de una obsesión",
        "hora_inicio": "17:29",
        "hora_fin": "18:19",
        "progreso": 18
    },
    {
        "canal": "Quiero.ar",
        "evento": "Los 60 +",
        "hora_inicio": "16:30",
        "hora_fin": "20:30",
        "progreso": 28
    },
    {
        "canal": "RaiItalia.ar",
        "evento": "Kilimangiaro",
        "hora_inicio": "16:30",
        "hora_fin": "18:30",
        "progreso": 57
    },
    {
        "canal": "RussiaToday.ar",
        "evento": "Rusia me abrió sus puertas",
        "hora_inicio": "17:30",
        "hora_fin": "18:00",
        "progreso": 28
    },
    {
        "canal": "Sony.ar",
        "evento": "Morbius",
        "hora_inicio": "17:00",
        "hora_fin": "18:55",
        "progreso": 33
    },
    {
        "canal": "Space.ar",
        "evento": "El cazador y la reina de hielo",
        "hora_inicio": "15:44",
        "hora_fin": "17:42",
        "progreso": 96
    },
    {
        "canal": "StarChannel.ar",
        "evento": "Maze Runner: La cura mortal",
        "hora_inicio": "16:42",
        "hora_fin": "19:42",
        "progreso": 31
    },
    {
        "canal": "StudioUniversal.ar",
        "evento": "Krakens y sirenas: conoce a los Gillman",
        "hora_inicio": "16:30",
        "hora_fin": "18:15",
        "progreso": 65
    },
    {
        "canal": "TCM.ar",
        "evento": "Dr. Jekyll y Mr. Hyde",
        "hora_inicio": "17:36",
        "hora_fin": "19:34",
        "progreso": 2
    },
    {
        "canal": "TECtv.ar",
        "evento": "TecTV",
        "hora_inicio": "16:00",
        "hora_fin": "20:00",
        "progreso": 41
    },
    {
        "canal": "Telediario.ar",
        "evento": "Resumen de noticias",
        "hora_inicio": "15:30",
        "hora_fin": "19:00",
        "progreso": 61
    },
    {
        "canal": "Telefe.ar",
        "evento": "DirecTV - DGO Presentan: Espiando la casa",
        "hora_inicio": "17:00",
        "hora_fin": "19:15",
        "progreso": 28
    },
    {
        "canal": "TelefeCordoba.ar",
        "evento": "Referentes",
        "hora_inicio": "17:30",
        "hora_fin": "18:00",
        "progreso": 28
    },
    {
        "canal": "TelefeRosario.ar",
        "evento": "A confirmar",
        "hora_inicio": "15:30",
        "hora_fin": "23:45",
        "progreso": 25
    },
    {
        "canal": "TelefeSantaFe.ar",
        "evento": "Los Simpson",
        "hora_inicio": "15:00",
        "hora_fin": "18:30",
        "progreso": 75
    },
    {
        "canal": "Telehit.ar",
        "evento": "Reggaepop",
        "hora_inicio": "17:30",
        "hora_fin": "18:30",
        "progreso": 14
    },
    {
        "canal": "Telemax.ar",
        "evento": "Lo mejor de Entre mate y mate",
        "hora_inicio": "16:00",
        "hora_fin": "18:00",
        "progreso": 82
    },
    {
        "canal": "teleSUR.ar",
        "evento": "Telesur Noticias",
        "hora_inicio": "17:30",
        "hora_fin": "18:00",
        "progreso": 28
    },
    {
        "canal": "TelevisionPublica.ar",
        "evento": "Unísono",
        "hora_inicio": "16:45",
        "hora_fin": "18:00",
        "progreso": 71
    },
    {
        "canal": "TierraMiaTV.ar",
        "evento": "TierraMia TV",
        "hora_inicio": "17:00",
        "hora_fin": "18:00",
        "progreso": 64
    },
    {
        "canal": "TLC.ar",
        "evento": "Una gran familia",
        "hora_inicio": "17:03",
        "hora_fin": "17:50",
        "progreso": 75
    },
    {
        "canal": "TLNovelas.ar",
        "evento": "En nombre del amor",
        "hora_inicio": "15:10",
        "hora_fin": "18:10",
        "progreso": 82
    },
    {
        "canal": "TN.ar",
        "evento": "Sábado en TN",
        "hora_inicio": "16:30",
        "hora_fin": "21:00",
        "progreso": 25
    },
    {
        "canal": "TNT.ar",
        "evento": "Focus: maestros de la estafa",
        "hora_inicio": "15:46",
        "hora_fin": "17:40",
        "progreso": 98
    },
    {
        "canal": "TNTSeries.ar",
        "evento": "CSI: Miami",
        "hora_inicio": "17:19",
        "hora_fin": "18:05",
        "progreso": 42
    },
    {
        "canal": "Tooncast.ar",
        "evento": "Hermano de Jorel",
        "hora_inicio": "17:30",
        "hora_fin": "17:41",
        "progreso": 76
    },
    {
        "canal": "TurismoVisionArgentina.ar",
        "evento": "Turismo Visión Argentina",
        "hora_inicio": "15:00",
        "hora_fin": "18:00",
        "progreso": 88
    },
    {
        "canal": "TV5.ar",
        "evento": "Questions pour un champion",
        "hora_inicio": "17:27",
        "hora_fin": "18:00",
        "progreso": 34
    },
    {
        "canal": "TVCiudad.ar",
        "evento": "NCC Reporte climático",
        "hora_inicio": "17:30",
        "hora_fin": "18:00",
        "progreso": 28
    },
    {
        "canal": "TVE.ar",
        "evento": "Denominación de origen",
        "hora_inicio": "17:00",
        "hora_fin": "17:56",
        "progreso": 68
    },
    {
        "canal": "TVGlobo.ar",
        "evento": "A confirmar",
        "hora_inicio": "14:40",
        "hora_fin": "20:30",
        "progreso": 50
    },
    {
        "canal": "TVNacionalUruguay.ar",
        "evento": "Todo deporte",
        "hora_inicio": "16:00",
        "hora_fin": "19:00",
        "progreso": 54
    },
    {
        "canal": "TVNCHILE.ar",
        "evento": "Chile conectado",
        "hora_inicio": "17:00",
        "hora_fin": "21:30",
        "progreso": 14
    },
    {
        "canal": "TVPublica.ar",
        "evento": "Unísono",
        "hora_inicio": "16:45",
        "hora_fin": "18:00",
        "progreso": 71
    },
    {
        "canal": "TyCSports.ar",
        "evento": "El postpartido de Canadá - Marruecos y la previa de Paraguay - Francia",
        "hora_inicio": "16:00",
        "hora_fin": "17:45",
        "progreso": 93
    },
    {
        "canal": "TyCSports2.ar",
        "evento": "TyC Sports 2",
        "hora_inicio": "12:00",
        "hora_fin": "00:00",
        "progreso": 47
    },
    {
        "canal": "UniversalTV.ar",
        "evento": "Policías de Chicago",
        "hora_inicio": "16:50",
        "hora_fin": "17:40",
        "progreso": 96
    },
    {
        "canal": "UruguayNaturalTV.ar",
        "evento": "Uruguay Natural TV",
        "hora_inicio": "16:00",
        "hora_fin": "20:00",
        "progreso": 41
    },
    {
        "canal": "Venus.ar",
        "evento": "18 años y lista para el romance",
        "hora_inicio": "16:33",
        "hora_fin": "18:00",
        "progreso": 75
    },
    {
        "canal": "Volver.ar",
        "evento": "Donde duermen dos, duermen tres",
        "hora_inicio": "17:00",
        "hora_fin": "18:45",
        "progreso": 36
    },
    {
        "canal": "VTV.ar",
        "evento": "Peñarol vs. Aguada",
        "hora_inicio": "16:30",
        "hora_fin": "19:00",
        "progreso": 45
    },
    {
        "canal": "WarnerChannel.ar",
        "evento": "El Hombre Araña 3",
        "hora_inicio": "16:56",
        "hora_fin": "19:34",
        "progreso": 26
    },
    {
        "canal": "ZooMoo.ar",
        "evento": "El show de los animales con Apestoso y Jake",
        "hora_inicio": "17:30",
        "hora_fin": "18:00",
        "progreso": 28
    }
]