[
    {
        "canal": "24/7CanaldeNoticias.ar",
        "evento": "La mañana es de la primera",
        "hora_inicio": "06:00",
        "hora_fin": "10:00",
        "progreso": 12
    },
    {
        "canal": "A24.ar",
        "evento": "Otra mañana",
        "hora_inicio": "06:00",
        "hora_fin": "10:00",
        "progreso": 12
    },
    {
        "canal": "AandE.ar",
        "evento": "No Data",
        "hora_inicio": "06:00",
        "hora_fin": "07:00",
        "progreso": 51
    },
    {
        "canal": "AMC.ar",
        "evento": "Planet Action",
        "hora_inicio": "06:30",
        "hora_fin": "07:00",
        "progreso": 2
    },
    {
        "canal": "AmericaSports.ar",
        "evento": "El escape del caburé",
        "hora_inicio": "06:30",
        "hora_fin": "07:30",
        "progreso": 1
    },
    {
        "canal": "AmericaTV.ar",
        "evento": "Arriba América",
        "hora_inicio": "06:00",
        "hora_fin": "08:00",
        "progreso": 25
    },
    {
        "canal": "AnimalPlanet.ar",
        "evento": "Los siete pecados animales",
        "hora_inicio": "06:00",
        "hora_fin": "06:46",
        "progreso": 67
    },
    {
        "canal": "ArgentinisimaSatelital.ar",
        "evento": "Argentinisima satelital",
        "hora_inicio": "06:00",
        "hora_fin": "09:00",
        "progreso": 17
    },
    {
        "canal": "Atreseries.ar",
        "evento": "Pop Up: Aquí no hay quien viva",
        "hora_inicio": "03:17",
        "hora_fin": "06:45",
        "progreso": 93
    },
    {
        "canal": "AXN.ar",
        "evento": "Hawaii-Five-O",
        "hora_inicio": "06:00",
        "hora_fin": "07:00",
        "progreso": 51
    },
    {
        "canal": "BabyTV.ar",
        "evento": "Amanence y brilla con los amigos de BabyTV",
        "hora_inicio": "06:30",
        "hora_fin": "07:00",
        "progreso": 2
    },
    {
        "canal": "Bloomberg.ar",
        "evento": "Bloomberg Brief",
        "hora_inicio": "06:00",
        "hora_fin": "07:00",
        "progreso": 51
    },
    {
        "canal": "C5N.ar",
        "evento": "Mañanas argentinas",
        "hora_inicio": "06:30",
        "hora_fin": "10:00",
        "progreso": 0
    },
    {
        "canal": "Canal21.ar",
        "evento": "Poliedro Latinoamericano",
        "hora_inicio": "05:30",
        "hora_fin": "08:00",
        "progreso": 40
    },
    {
        "canal": "Canal26.ar",
        "evento": "El pulso",
        "hora_inicio": "06:00",
        "hora_fin": "08:00",
        "progreso": 25
    },
    {
        "canal": "CanalDeLaCiudad.ar",
        "evento": "Descomunales",
        "hora_inicio": "04:00",
        "hora_fin": "07:00",
        "progreso": 83
    },
    {
        "canal": "CanalDeLaMusica.ar",
        "evento": "Full Love",
        "hora_inicio": "06:30",
        "hora_fin": "07:00",
        "progreso": 2
    },
    {
        "canal": "CanalRural.ar",
        "evento": "Noticiero primera edición",
        "hora_inicio": "06:30",
        "hora_fin": "07:00",
        "progreso": 2
    },
    {
        "canal": "Cartoonito.ar",
        "evento": "No Data",
        "hora_inicio": "06:00",
        "hora_fin": "07:00",
        "progreso": 51
    },
    {
        "canal": "CartoonNetwork.ar",
        "evento": "El mundo de Craig",
        "hora_inicio": "06:25",
        "hora_fin": "06:50",
        "progreso": 23
    },
    {
        "canal": "CineAr.ar",
        "evento": "Ulises, un alma desbordada",
        "hora_inicio": "06:00",
        "hora_fin": "08:00",
        "progreso": 25
    },
    {
        "canal": "Cinecanal.ar",
        "evento": "Henry y Klauss: maestros de la magia",
        "hora_inicio": "04:03",
        "hora_fin": "07:00",
        "progreso": 83
    },
    {
        "canal": "Cinelatino.ar",
        "evento": "Casa por cárcel",
        "hora_inicio": "05:15",
        "hora_fin": "06:55",
        "progreso": 75
    },
    {
        "canal": "Cinemax(Sur).ar",
        "evento": "Mi gran boda griega 2",
        "hora_inicio": "06:00",
        "hora_fin": "07:20",
        "progreso": 38
    },
    {
        "canal": "Cinemax.ar",
        "evento": "Eterno resplandor de una mente sin recuerdos",
        "hora_inicio": "05:42",
        "hora_fin": "09:00",
        "progreso": 24
    },
    {
        "canal": "CiudadMagazine.ar",
        "evento": "Vida Purita",
        "hora_inicio": "06:30",
        "hora_fin": "07:00",
        "progreso": 2
    },
    {
        "canal": "CN23.ar",
        "evento": "CN 23",
        "hora_inicio": "06:00",
        "hora_fin": "07:00",
        "progreso": 51
    },
    {
        "canal": "CNN.ar",
        "evento": "Marketplace Europe",
        "hora_inicio": "17:45",
        "hora_fin": "12:30",
        "progreso": 68
    },
    {
        "canal": "CNNenEspanol.ar",
        "evento": "Perspectivas de México",
        "hora_inicio": "06:00",
        "hora_fin": "07:00",
        "progreso": 51
    },
    {
        "canal": "ComedyCentral.ar",
        "evento": "Awkwafina Is Nora from Queens",
        "hora_inicio": "06:20",
        "hora_fin": "06:45",
        "progreso": 43
    },
    {
        "canal": "ConexionEducativa.ar",
        "evento": "Conexión educativa",
        "hora_inicio": "06:00",
        "hora_fin": "09:00",
        "progreso": 17
    },
    {
        "canal": "ConstruirTV.ar",
        "evento": "Iberoamérica en órbita",
        "hora_inicio": "06:30",
        "hora_fin": "07:30",
        "progreso": 1
    },
    {
        "canal": "CronicaTV.ar",
        "evento": "La primera",
        "hora_inicio": "06:00",
        "hora_fin": "08:00",
        "progreso": 25
    },
    {
        "canal": "Discovery.ar",
        "evento": "Supervivencia al desnudo",
        "hora_inicio": "06:25",
        "hora_fin": "07:13",
        "progreso": 12
    },
    {
        "canal": "DiscoveryChannel.ar",
        "evento": "Supervivencia al desnudo",
        "hora_inicio": "06:25",
        "hora_fin": "07:13",
        "progreso": 12
    },
    {
        "canal": "DiscoveryHomeAndHealth.ar",
        "evento": "Sala de emergencias: historias inéditas",
        "hora_inicio": "06:00",
        "hora_fin": "06:50",
        "progreso": 61
    },
    {
        "canal": "DiscoveryKids.ar",
        "evento": "¡Agente Binky al rescate!",
        "hora_inicio": "06:17",
        "hora_fin": "06:39",
        "progreso": 62
    },
    {
        "canal": "DiscoveryTurbo.ar",
        "evento": "Alto octanaje en Las Vegas",
        "hora_inicio": "06:26",
        "hora_fin": "07:12",
        "progreso": 10
    },
    {
        "canal": "DisneyChannel.ar",
        "evento": "Prodigiosa: las aventuras de Ladybug",
        "hora_inicio": "06:09",
        "hora_fin": "06:32",
        "progreso": 94
    },
    {
        "canal": "DisneyJunior.ar",
        "evento": "Doctora Juguetes",
        "hora_inicio": "06:07",
        "hora_fin": "06:31",
        "progreso": 99
    },
    {
        "canal": "DisneyXD.ar",
        "evento": "No Data",
        "hora_inicio": "06:00",
        "hora_fin": "07:00",
        "progreso": 51
    },
    {
        "canal": "Dreamworks.ar",
        "evento": "No Data",
        "hora_inicio": "06:00",
        "hora_fin": "07:00",
        "progreso": 51
    },
    {
        "canal": "E!.ar",
        "evento": "No Data",
        "hora_inicio": "06:00",
        "hora_fin": "07:00",
        "progreso": 51
    },
    {
        "canal": "ElGarageTv.ar",
        "evento": "Visión motor",
        "hora_inicio": "06:30",
        "hora_fin": "07:00",
        "progreso": 2
    },
    {
        "canal": "ElGourmet.ar",
        "evento": "Infomerciales",
        "hora_inicio": "06:30",
        "hora_fin": "07:00",
        "progreso": 2
    },
    {
        "canal": "ELNueve.ar",
        "evento": "TL 9 al amanecer a las 6",
        "hora_inicio": "06:00",
        "hora_fin": "07:00",
        "progreso": 51
    },
    {
        "canal": "ELTrece.ar",
        "evento": "Tiempo del tiempo",
        "hora_inicio": "06:30",
        "hora_fin": "07:00",
        "progreso": 2
    },
    {
        "canal": "Encuentro.ar",
        "evento": "Presidio",
        "hora_inicio": "06:30",
        "hora_fin": "07:00",
        "progreso": 2
    },
    {
        "canal": "ESPN.ar",
        "evento": "SportsCenter",
        "hora_inicio": "06:00",
        "hora_fin": "07:00",
        "progreso": 51
    },
    {
        "canal": "ESPN2.ar",
        "evento": "Final femenina",
        "hora_inicio": "06:00",
        "hora_fin": "07:00",
        "progreso": 51
    },
    {
        "canal": "ESPN3.ar",
        "evento": "Aguas arriba",
        "hora_inicio": "06:30",
        "hora_fin": "07:00",
        "progreso": 2
    },
    {
        "canal": "ESPN4.ar",
        "evento": "Detroit Tigers vs. Chicago Cubs",
        "hora_inicio": "04:00",
        "hora_fin": "07:00",
        "progreso": 83
    },
    {
        "canal": "ESPNExtra.ar",
        "evento": "No Data",
        "hora_inicio": "06:00",
        "hora_fin": "07:00",
        "progreso": 51
    },
    {
        "canal": "ESPNSur.ar",
        "evento": "SportsCenter",
        "hora_inicio": "06:00",
        "hora_fin": "07:00",
        "progreso": 51
    },
    {
        "canal": "ESPNSur2.ar",
        "evento": "Fútbol Conmebol Copa Sudamericana",
        "hora_inicio": "05:00",
        "hora_fin": "07:00",
        "progreso": 75
    },
    {
        "canal": "ESPNSur3.ar",
        "evento": "ESPN Knockout",
        "hora_inicio": "05:00",
        "hora_fin": "07:00",
        "progreso": 75
    },
    {
        "canal": "ESPNSur4.ar",
        "evento": "Béisbol MLB",
        "hora_inicio": "05:00",
        "hora_fin": "08:00",
        "progreso": 50
    },
    {
        "canal": "EuropaEuropa.ar",
        "evento": "Historia de un crimen",
        "hora_inicio": "04:15",
        "hora_fin": "06:35",
        "progreso": 97
    },
    {
        "canal": "EWTN.ar",
        "evento": "Gertrudis, la grande. Vida de Santa Gertrudis de Helfta",
        "hora_inicio": "06:30",
        "hora_fin": "07:00",
        "progreso": 2
    },
    {
        "canal": "filmAndarts.ar",
        "evento": "El show de Graham Norton",
        "hora_inicio": "06:30",
        "hora_fin": "07:30",
        "progreso": 1
    },
    {
        "canal": "FOX Sports",
        "evento": "La vuelta",
        "hora_inicio": "05:00",
        "hora_fin": "07:00",
        "progreso": 75
    },
    {
        "canal": "FOXSports2.ar",
        "evento": "Paradise Extreme",
        "hora_inicio": "06:30",
        "hora_fin": "07:00",
        "progreso": 2
    },
    {
        "canal": "FOXSports3.ar",
        "evento": "Oakland Athletics vs. Arizona D-Backs",
        "hora_inicio": "04:00",
        "hora_fin": "07:00",
        "progreso": 83
    },
    {
        "canal": "FOXSportsConoSur.ar",
        "evento": "La vuelta",
        "hora_inicio": "05:00",
        "hora_fin": "07:00",
        "progreso": 75
    },
    {
        "canal": "France24enEspanol.ar",
        "evento": "Noticias",
        "hora_inicio": "06:30",
        "hora_fin": "06:40",
        "progreso": 8
    },
    {
        "canal": "FX.ar",
        "evento": "The Amazing Race",
        "hora_inicio": "04:42",
        "hora_fin": "07:00",
        "progreso": 78
    },
    {
        "canal": "FXMovies.ar",
        "evento": "No Data",
        "hora_inicio": "06:00",
        "hora_fin": "07:00",
        "progreso": 51
    },
    {
        "canal": "GaliciaTV.ar",
        "evento": "O termómetro",
        "hora_inicio": "06:30",
        "hora_fin": "08:45",
        "progreso": 0
    },
    {
        "canal": "Glitz.ar",
        "evento": "No Data",
        "hora_inicio": "06:00",
        "hora_fin": "07:00",
        "progreso": 51
    },
    {
        "canal": "Golden.ar",
        "evento": "Juega conmigo",
        "hora_inicio": "06:06",
        "hora_fin": "07:31",
        "progreso": 29
    },
    {
        "canal": "GoldenEdge.ar",
        "evento": "Golpes del destino",
        "hora_inicio": "05:14",
        "hora_fin": "07:36",
        "progreso": 54
    },
    {
        "canal": "GolfChannel.ar",
        "evento": "Round 1",
        "hora_inicio": "05:30",
        "hora_fin": "07:00",
        "progreso": 67
    },
    {
        "canal": "GolTV.ar",
        "evento": "No Data",
        "hora_inicio": "06:00",
        "hora_fin": "07:00",
        "progreso": 51
    },
    {
        "canal": "HAPSATV.ar",
        "evento": "Turf en vivo - Palermo, San Isidro y La Plata",
        "hora_inicio": "04:00",
        "hora_fin": "08:00",
        "progreso": 62
    },
    {
        "canal": "HBO.ar",
        "evento": "Los ángeles de Charlie: Al límite",
        "hora_inicio": "06:11",
        "hora_fin": "08:01",
        "progreso": 18
    },
    {
        "canal": "HBO2.ar",
        "evento": "Un portero muy improbable",
        "hora_inicio": "06:00",
        "hora_fin": "07:36",
        "progreso": 32
    },
    {
        "canal": "HBOFamily.ar",
        "evento": "Open Season: Tontos por el susto",
        "hora_inicio": "05:45",
        "hora_fin": "07:13",
        "progreso": 52
    },
    {
        "canal": "HBOMundi.ar",
        "evento": "Drácula",
        "hora_inicio": "06:00",
        "hora_fin": "07:15",
        "progreso": 41
    },
    {
        "canal": "HBOOeste.ar",
        "evento": "Turno nocturno",
        "hora_inicio": "05:18",
        "hora_fin": "07:13",
        "progreso": 63
    },
    {
        "canal": "HBOPlus(Panamericano).ar",
        "evento": "Batman Azteca: Choque de imperios",
        "hora_inicio": "06:00",
        "hora_fin": "07:30",
        "progreso": 34
    },
    {
        "canal": "HBOPlusEste.ar",
        "evento": "Batman Azteca: Choque de imperios",
        "hora_inicio": "06:00",
        "hora_fin": "07:30",
        "progreso": 34
    },
    {
        "canal": "HBOPlusPanregional.ar",
        "evento": "No Data",
        "hora_inicio": "06:00",
        "hora_fin": "07:00",
        "progreso": 51
    },
    {
        "canal": "HBOPop.ar",
        "evento": "Chiquito pero peligroso",
        "hora_inicio": "06:00",
        "hora_fin": "07:39",
        "progreso": 31
    },
    {
        "canal": "HBOSignature.ar",
        "evento": "Elizabeth Taylor - Las cintas perdidas",
        "hora_inicio": "06:00",
        "hora_fin": "07:52",
        "progreso": 27
    },
    {
        "canal": "HBOXtreme(Oeste).ar",
        "evento": "No Data",
        "hora_inicio": "06:00",
        "hora_fin": "07:00",
        "progreso": 51
    },
    {
        "canal": "HBOXtreme(Panamericano).ar",
        "evento": "Matrix resurrecciones",
        "hora_inicio": "06:00",
        "hora_fin": "08:31",
        "progreso": 20
    },
    {
        "canal": "HBOXtreme(Panregional).ar",
        "evento": "No Data",
        "hora_inicio": "06:00",
        "hora_fin": "07:00",
        "progreso": 51
    },
    {
        "canal": "HBOXtreme.ar",
        "evento": "Matrix resurrecciones",
        "hora_inicio": "06:00",
        "hora_fin": "08:31",
        "progreso": 20
    },
    {
        "canal": "HGTV.ar",
        "evento": "La mejor inversión",
        "hora_inicio": "06:23",
        "hora_fin": "06:46",
        "progreso": 34
    },
    {
        "canal": "HispanTV.ar",
        "evento": "Entre líneas",
        "hora_inicio": "06:30",
        "hora_fin": "07:00",
        "progreso": 2
    },
    {
        "canal": "History.ar",
        "evento": "El precio de la historia",
        "hora_inicio": "06:00",
        "hora_fin": "06:40",
        "progreso": 77
    },
    {
        "canal": "History2.ar",
        "evento": "Inventos de la antigüedad",
        "hora_inicio": "06:13",
        "hora_fin": "07:10",
        "progreso": 31
    },
    {
        "canal": "HolaTV.ar",
        "evento": "Tendencias del siglo XXI",
        "hora_inicio": "06:30",
        "hora_fin": "07:00",
        "progreso": 2
    },
    {
        "canal": "HTV.ar",
        "evento": "HTV",
        "hora_inicio": "01:00",
        "hora_fin": "09:00",
        "progreso": 68
    },
    {
        "canal": "I-SAT.ar",
        "evento": "No Data",
        "hora_inicio": "06:00",
        "hora_fin": "07:00",
        "progreso": 51
    },
    {
        "canal": "InvestigationDiscovery.ar",
        "evento": "Víctimas del amor",
        "hora_inicio": "06:00",
        "hora_fin": "06:45",
        "progreso": 68
    },
    {
        "canal": "IVC.ar",
        "evento": "No Data",
        "hora_inicio": "06:00",
        "hora_fin": "07:00",
        "progreso": 51
    },
    {
        "canal": "KZO.ar",
        "evento": "No Data",
        "hora_inicio": "06:00",
        "hora_fin": "07:00",
        "progreso": 51
    },
    {
        "canal": "LasEstrellas.ar",
        "evento": "Mujer, casos de la vida real",
        "hora_inicio": "06:20",
        "hora_fin": "08:10",
        "progreso": 9
    },
    {
        "canal": "Lifetime.ar",
        "evento": "No Data",
        "hora_inicio": "06:00",
        "hora_fin": "07:00",
        "progreso": 51
    },
    {
        "canal": "LN+.ar",
        "evento": "Pre mañana",
        "hora_inicio": "06:00",
        "hora_fin": "06:45",
        "progreso": 68
    },
    {
        "canal": "MasChic.ar",
        "evento": "The Walking Dead",
        "hora_inicio": "06:00",
        "hora_fin": "06:50",
        "progreso": 61
    },
    {
        "canal": "Metro.ar",
        "evento": "Agro TV",
        "hora_inicio": "06:00",
        "hora_fin": "07:00",
        "progreso": 51
    },
    {
        "canal": "MTV.ar",
        "evento": "Ridiculousness",
        "hora_inicio": "06:15",
        "hora_fin": "06:40",
        "progreso": 63
    },
    {
        "canal": "MTVHits.ar",
        "evento": "No Data",
        "hora_inicio": "06:00",
        "hora_fin": "07:00",
        "progreso": 51
    },
    {
        "canal": "MuchMusic.ar",
        "evento": "No Data",
        "hora_inicio": "06:00",
        "hora_fin": "07:00",
        "progreso": 51
    },
    {
        "canal": "Musictop.ar",
        "evento": "MusicTop",
        "hora_inicio": "06:00",
        "hora_fin": "07:00",
        "progreso": 51
    },
    {
        "canal": "NatGeoKids.ar",
        "evento": "No Data",
        "hora_inicio": "06:00",
        "hora_fin": "07:00",
        "progreso": 51
    },
    {
        "canal": "NationalGeographic.ar",
        "evento": "Secreto en los océanos",
        "hora_inicio": "05:46",
        "hora_fin": "06:31",
        "progreso": 99
    },
    {
        "canal": "NationalGeographicWild.ar",
        "evento": "No Data",
        "hora_inicio": "06:00",
        "hora_fin": "07:00",
        "progreso": 51
    },
    {
        "canal": "NBATV.ar",
        "evento": "The Association",
        "hora_inicio": "05:00",
        "hora_fin": "07:00",
        "progreso": 75
    },
    {
        "canal": "NetTV.ar",
        "evento": "El señor de los cielos",
        "hora_inicio": "05:00",
        "hora_fin": "07:00",
        "progreso": 75
    },
    {
        "canal": "Nick2.ar",
        "evento": "No Data",
        "hora_inicio": "06:00",
        "hora_fin": "07:00",
        "progreso": 51
    },
    {
        "canal": "NickJr..ar",
        "evento": "Santiago de los mares",
        "hora_inicio": "06:20",
        "hora_fin": "06:45",
        "progreso": 43
    },
    {
        "canal": "NickToons.ar",
        "evento": "No Data",
        "hora_inicio": "06:00",
        "hora_fin": "07:00",
        "progreso": 51
    },
    {
        "canal": "Pakapaka.ar",
        "evento": "Medialuna",
        "hora_inicio": "06:30",
        "hora_fin": "07:00",
        "progreso": 2
    },
    {
        "canal": "ParamountNetwork.ar",
        "evento": "No Data",
        "hora_inicio": "06:00",
        "hora_fin": "07:00",
        "progreso": 51
    },
    {
        "canal": "Pasiones.ar",
        "evento": "Éramos seis",
        "hora_inicio": "06:00",
        "hora_fin": "07:00",
        "progreso": 51
    },
    {
        "canal": "PenthouseGold.ar",
        "evento": "4 nerds tragaleche",
        "hora_inicio": "06:00",
        "hora_fin": "07:42",
        "progreso": 30
    },
    {
        "canal": "Playboy.ar",
        "evento": "Mixed Love",
        "hora_inicio": "06:00",
        "hora_fin": "07:29",
        "progreso": 34
    },
    {
        "canal": "Quiero.ar",
        "evento": "Quiero clásicos",
        "hora_inicio": "05:00",
        "hora_fin": "07:00",
        "progreso": 75
    },
    {
        "canal": "RaiItalia.ar",
        "evento": "Italia A/R",
        "hora_inicio": "06:15",
        "hora_fin": "06:45",
        "progreso": 52
    },
    {
        "canal": "RussiaToday.ar",
        "evento": "Ahí les va",
        "hora_inicio": "06:30",
        "hora_fin": "07:00",
        "progreso": 2
    },
    {
        "canal": "SmithsonianChannel.ar",
        "evento": "No Data",
        "hora_inicio": "06:00",
        "hora_fin": "07:00",
        "progreso": 51
    },
    {
        "canal": "Sony.ar",
        "evento": "The Good Doctor",
        "hora_inicio": "06:00",
        "hora_fin": "07:00",
        "progreso": 51
    },
    {
        "canal": "Space.ar",
        "evento": "El legado de las mentiras",
        "hora_inicio": "06:00",
        "hora_fin": "07:34",
        "progreso": 32
    },
    {
        "canal": "StarAction(Oeste).ar",
        "evento": "No Data",
        "hora_inicio": "06:00",
        "hora_fin": "07:00",
        "progreso": 51
    },
    {
        "canal": "StarAction.ar",
        "evento": "No Data",
        "hora_inicio": "06:00",
        "hora_fin": "07:00",
        "progreso": 51
    },
    {
        "canal": "StarChannel.ar",
        "evento": "Castle",
        "hora_inicio": "05:52",
        "hora_fin": "07:00",
        "progreso": 57
    },
    {
        "canal": "StarCinema.ar",
        "evento": "No Data",
        "hora_inicio": "06:00",
        "hora_fin": "07:00",
        "progreso": 51
    },
    {
        "canal": "StarClassics.ar",
        "evento": "No Data",
        "hora_inicio": "06:00",
        "hora_fin": "07:00",
        "progreso": 51
    },
    {
        "canal": "StarComedy.ar",
        "evento": "No Data",
        "hora_inicio": "06:00",
        "hora_fin": "07:00",
        "progreso": 51
    },
    {
        "canal": "StarFun(Oeste).ar",
        "evento": "No Data",
        "hora_inicio": "06:00",
        "hora_fin": "07:00",
        "progreso": 51
    },
    {
        "canal": "StarFun.ar",
        "evento": "No Data",
        "hora_inicio": "06:00",
        "hora_fin": "07:00",
        "progreso": 51
    },
    {
        "canal": "StarHits.ar",
        "evento": "No Data",
        "hora_inicio": "06:00",
        "hora_fin": "07:00",
        "progreso": 51
    },
    {
        "canal": "StarLife.ar",
        "evento": "No Data",
        "hora_inicio": "06:00",
        "hora_fin": "07:00",
        "progreso": 51
    },
    {
        "canal": "StarSeries(Oeste).ar",
        "evento": "No Data",
        "hora_inicio": "06:00",
        "hora_fin": "07:00",
        "progreso": 51
    },
    {
        "canal": "StarSeries.ar",
        "evento": "No Data",
        "hora_inicio": "06:00",
        "hora_fin": "07:00",
        "progreso": 51
    },
    {
        "canal": "StudioUniversal.ar",
        "evento": "Mistletoe Murders",
        "hora_inicio": "06:30",
        "hora_fin": "07:15",
        "progreso": 1
    },
    {
        "canal": "Syfy.ar",
        "evento": "No Data",
        "hora_inicio": "06:00",
        "hora_fin": "07:00",
        "progreso": 51
    },
    {
        "canal": "TaTeTi.ar",
        "evento": "No Data",
        "hora_inicio": "06:00",
        "hora_fin": "07:00",
        "progreso": 51
    },
    {
        "canal": "TBS.ar",
        "evento": "No Data",
        "hora_inicio": "06:00",
        "hora_fin": "07:00",
        "progreso": 51
    },
    {
        "canal": "TCM.ar",
        "evento": "Hollywood One on One",
        "hora_inicio": "06:10",
        "hora_fin": "06:45",
        "progreso": 59
    },
    {
        "canal": "TECtv.ar",
        "evento": "TecTV",
        "hora_inicio": "04:00",
        "hora_fin": "08:00",
        "progreso": 62
    },
    {
        "canal": "Telediario.ar",
        "evento": "Resumen de noticias",
        "hora_inicio": "05:00",
        "hora_fin": "07:00",
        "progreso": 75
    },
    {
        "canal": "Telefe.ar",
        "evento": "Disney Jr.",
        "hora_inicio": "06:00",
        "hora_fin": "06:45",
        "progreso": 68
    },
    {
        "canal": "TelefeCordoba.ar",
        "evento": "Cierre de transmisión",
        "hora_inicio": "01:30",
        "hora_fin": "07:00",
        "progreso": 91
    },
    {
        "canal": "TelefeRosario.ar",
        "evento": "Fin de transmisión",
        "hora_inicio": "06:00",
        "hora_fin": "07:00",
        "progreso": 51
    },
    {
        "canal": "TelefeSantaFe.ar",
        "evento": "Fin de transmisión",
        "hora_inicio": "06:00",
        "hora_fin": "07:00",
        "progreso": 51
    },
    {
        "canal": "Telehit.ar",
        "evento": "Top 10",
        "hora_inicio": "06:00",
        "hora_fin": "07:00",
        "progreso": 51
    },
    {
        "canal": "Telemax.ar",
        "evento": "Datos curiosos",
        "hora_inicio": "06:00",
        "hora_fin": "07:00",
        "progreso": 51
    },
    {
        "canal": "TelemundoInternacional.ar",
        "evento": "No Data",
        "hora_inicio": "06:00",
        "hora_fin": "07:00",
        "progreso": 51
    },
    {
        "canal": "teleSUR.ar",
        "evento": "Telesur Noticias",
        "hora_inicio": "06:30",
        "hora_fin": "07:00",
        "progreso": 2
    },
    {
        "canal": "TelevisionPublica.ar",
        "evento": "Fin de transmisión",
        "hora_inicio": "01:00",
        "hora_fin": "06:45",
        "progreso": 95
    },
    {
        "canal": "TierraMiaTV.ar",
        "evento": "TierraMia TV",
        "hora_inicio": "06:00",
        "hora_fin": "09:00",
        "progreso": 17
    },
    {
        "canal": "TLC.ar",
        "evento": "Mi gran boda gitana",
        "hora_inicio": "06:00",
        "hora_fin": "06:50",
        "progreso": 61
    },
    {
        "canal": "TLNovelas.ar",
        "evento": "Para volver a amar",
        "hora_inicio": "05:50",
        "hora_fin": "07:20",
        "progreso": 45
    },
    {
        "canal": "TN.ar",
        "evento": "TN de 6 a 10",
        "hora_inicio": "06:00",
        "hora_fin": "10:00",
        "progreso": 12
    },
    {
        "canal": "TNT.ar",
        "evento": "El Hombre Araña",
        "hora_inicio": "06:00",
        "hora_fin": "07:43",
        "progreso": 29
    },
    {
        "canal": "TNTSeries.ar",
        "evento": "La ley y el orden: UVE",
        "hora_inicio": "06:00",
        "hora_fin": "06:42",
        "progreso": 73
    },
    {
        "canal": "Tooncast.ar",
        "evento": "La Mansión Foster para Amigos Imaginarios",
        "hora_inicio": "06:23",
        "hora_fin": "06:45",
        "progreso": 35
    },
    {
        "canal": "TruTV.ar",
        "evento": "No Data",
        "hora_inicio": "06:00",
        "hora_fin": "07:00",
        "progreso": 51
    },
    {
        "canal": "TurismoVisionArgentina.ar",
        "evento": "Turismo Visión Argentina",
        "hora_inicio": "06:00",
        "hora_fin": "09:00",
        "progreso": 17
    },
    {
        "canal": "TV5.ar",
        "evento": "Télématin",
        "hora_inicio": "06:26",
        "hora_fin": "09:00",
        "progreso": 3
    },
    {
        "canal": "TVCiudad.ar",
        "evento": "Videoclips",
        "hora_inicio": "04:00",
        "hora_fin": "07:00",
        "progreso": 83
    },
    {
        "canal": "TVCortos.ar",
        "evento": "No Data",
        "hora_inicio": "06:00",
        "hora_fin": "07:00",
        "progreso": 51
    },
    {
        "canal": "TVE.ar",
        "evento": "#Mañaneros",
        "hora_inicio": "05:35",
        "hora_fin": "09:20",
        "progreso": 24
    },
    {
        "canal": "TVGlobo.ar",
        "evento": "Coração acelerado",
        "hora_inicio": "06:15",
        "hora_fin": "07:05",
        "progreso": 31
    },
    {
        "canal": "TVNacionalUruguay.ar",
        "evento": "El recreo",
        "hora_inicio": "05:00",
        "hora_fin": "07:00",
        "progreso": 75
    },
    {
        "canal": "TVNCHILE.ar",
        "evento": "Frutos del país",
        "hora_inicio": "06:30",
        "hora_fin": "07:00",
        "progreso": 2
    },
    {
        "canal": "TVPublica.ar",
        "evento": "Fin de transmisión",
        "hora_inicio": "01:00",
        "hora_fin": "06:45",
        "progreso": 95
    },
    {
        "canal": "TyCSports.ar",
        "evento": "Sportia",
        "hora_inicio": "06:00",
        "hora_fin": "07:00",
        "progreso": 51
    },
    {
        "canal": "TyCSports2.ar",
        "evento": "TyC Sports 2",
        "hora_inicio": "00:00",
        "hora_fin": "12:00",
        "progreso": 54
    },
    {
        "canal": "UniversalTV.ar",
        "evento": "La ley y el orden: UVE",
        "hora_inicio": "06:00",
        "hora_fin": "06:55",
        "progreso": 56
    },
    {
        "canal": "UruguayNaturalTV.ar",
        "evento": "Uruguay Natural TV",
        "hora_inicio": "04:00",
        "hora_fin": "08:00",
        "progreso": 62
    },
    {
        "canal": "Venus.ar",
        "evento": "Workplace Threeways Full Service Assistants",
        "hora_inicio": "06:00",
        "hora_fin": "07:30",
        "progreso": 34
    },
    {
        "canal": "VH1.ar",
        "evento": "No Data",
        "hora_inicio": "06:00",
        "hora_fin": "07:00",
        "progreso": 51
    },
    {
        "canal": "VH1MegaHits.ar",
        "evento": "No Data",
        "hora_inicio": "06:00",
        "hora_fin": "07:00",
        "progreso": 51
    },
    {
        "canal": "Viajar.ar",
        "evento": "No Data",
        "hora_inicio": "06:00",
        "hora_fin": "07:00",
        "progreso": 51
    },
    {
        "canal": "Volver.ar",
        "evento": "Gasoleros",
        "hora_inicio": "06:00",
        "hora_fin": "07:00",
        "progreso": 51
    },
    {
        "canal": "VTV.ar",
        "evento": "VTV Noticias - 3º edición",
        "hora_inicio": "06:00",
        "hora_fin": "07:00",
        "progreso": 51
    },
    {
        "canal": "WarnerChannel.ar",
        "evento": "Cobra Kai",
        "hora_inicio": "06:21",
        "hora_fin": "07:17",
        "progreso": 17
    },
    {
        "canal": "ZooMoo.ar",
        "evento": "Jelly Jamm",
        "hora_inicio": "06:30",
        "hora_fin": "06:45",
        "progreso": 5
    }
]