[
    {
        "canal": "24/7CanaldeNoticias.ar",
        "evento": "Trasnoche de 24/7",
        "hora_inicio": "22:00",
        "hora_fin": "06:00",
        "progreso": 60
    },
    {
        "canal": "A24.ar",
        "evento": "TeveCompras",
        "hora_inicio": "02:00",
        "hora_fin": "03:00",
        "progreso": 80
    },
    {
        "canal": "AMC.ar",
        "evento": "Priest, el vengador",
        "hora_inicio": "02:10",
        "hora_fin": "03:45",
        "progreso": 40
    },
    {
        "canal": "AmericaSports.ar",
        "evento": "El escape del caburé",
        "hora_inicio": "02:00",
        "hora_fin": "03:00",
        "progreso": 80
    },
    {
        "canal": "AmericaTV.ar",
        "evento": "Intrusos",
        "hora_inicio": "02:00",
        "hora_fin": "03:30",
        "progreso": 53
    },
    {
        "canal": "AnimalPlanet.ar",
        "evento": "Dr. Jeff, veterinario",
        "hora_inicio": "02:40",
        "hora_fin": "03:30",
        "progreso": 16
    },
    {
        "canal": "ArgentinisimaSatelital.ar",
        "evento": "Argentinisima satelital",
        "hora_inicio": "00:00",
        "hora_fin": "03:00",
        "progreso": 93
    },
    {
        "canal": "Atreseries.ar",
        "evento": "Acoso",
        "hora_inicio": "02:12",
        "hora_fin": "02:57",
        "progreso": 80
    },
    {
        "canal": "AXN.ar",
        "evento": "Hawaii-Five-O",
        "hora_inicio": "02:35",
        "hora_fin": "03:25",
        "progreso": 26
    },
    {
        "canal": "BabyTV.ar",
        "evento": "Dulces sueños",
        "hora_inicio": "02:30",
        "hora_fin": "03:00",
        "progreso": 61
    },
    {
        "canal": "Bloomberg.ar",
        "evento": "Bloomberg Daybreak: Europe",
        "hora_inicio": "02:00",
        "hora_fin": "03:00",
        "progreso": 80
    },
    {
        "canal": "C5N.ar",
        "evento": "Minuto uno",
        "hora_inicio": "01:00",
        "hora_fin": "03:00",
        "progreso": 90
    },
    {
        "canal": "Canal21.ar",
        "evento": "Diálogos con la vida",
        "hora_inicio": "02:00",
        "hora_fin": "03:00",
        "progreso": 80
    },
    {
        "canal": "Canal26.ar",
        "evento": "26 Extra",
        "hora_inicio": "01:00",
        "hora_fin": "03:00",
        "progreso": 90
    },
    {
        "canal": "CanalDeLaCiudad.ar",
        "evento": "Fila 5",
        "hora_inicio": "01:00",
        "hora_fin": "03:00",
        "progreso": 90
    },
    {
        "canal": "CanalDeLaMusica.ar",
        "evento": "Ranking urbano",
        "hora_inicio": "02:30",
        "hora_fin": "03:00",
        "progreso": 61
    },
    {
        "canal": "CanalRural.ar",
        "evento": "Córdoba rural",
        "hora_inicio": "02:30",
        "hora_fin": "03:00",
        "progreso": 61
    },
    {
        "canal": "CartoonNetwork.ar",
        "evento": "Escandalosos",
        "hora_inicio": "02:40",
        "hora_fin": "02:50",
        "progreso": 84
    },
    {
        "canal": "CineAr.ar",
        "evento": "Punto muerto",
        "hora_inicio": "02:00",
        "hora_fin": "04:00",
        "progreso": 40
    },
    {
        "canal": "Cinecanal.ar",
        "evento": "Prueba de fuego",
        "hora_inicio": "02:33",
        "hora_fin": "04:39",
        "progreso": 12
    },
    {
        "canal": "Cinelatino.ar",
        "evento": "Viaje redondo",
        "hora_inicio": "01:15",
        "hora_fin": "03:00",
        "progreso": 88
    },
    {
        "canal": "Cinemax(Sur).ar",
        "evento": "El francotirador",
        "hora_inicio": "00:38",
        "hora_fin": "03:02",
        "progreso": 90
    },
    {
        "canal": "Cinemax.ar",
        "evento": "El cazador y la reina de hielo",
        "hora_inicio": "02:19",
        "hora_fin": "04:16",
        "progreso": 25
    },
    {
        "canal": "CiudadMagazine.ar",
        "evento": "Mshow",
        "hora_inicio": "02:30",
        "hora_fin": "03:30",
        "progreso": 30
    },
    {
        "canal": "CN23.ar",
        "evento": "CN 23",
        "hora_inicio": "02:00",
        "hora_fin": "03:00",
        "progreso": 80
    },
    {
        "canal": "CNN.ar",
        "evento": "World Sport",
        "hora_inicio": "02:45",
        "hora_fin": "03:00",
        "progreso": 22
    },
    {
        "canal": "CNNenEspanol.ar",
        "evento": "The Story Is: With Elex Michaelson",
        "hora_inicio": "02:00",
        "hora_fin": "03:00",
        "progreso": 80
    },
    {
        "canal": "ComedyCentral.ar",
        "evento": "South Park",
        "hora_inicio": "02:35",
        "hora_fin": "03:00",
        "progreso": 53
    },
    {
        "canal": "ConexionEducativa.ar",
        "evento": "Conexión educativa",
        "hora_inicio": "00:00",
        "hora_fin": "03:00",
        "progreso": 93
    },
    {
        "canal": "ConstruirTV.ar",
        "evento": "Construir TV Infantil",
        "hora_inicio": "02:30",
        "hora_fin": "03:30",
        "progreso": 30
    },
    {
        "canal": "CronicaTV.ar",
        "evento": "El valor de tus joyas",
        "hora_inicio": "02:30",
        "hora_fin": "04:00",
        "progreso": 20
    },
    {
        "canal": "Discovery.ar",
        "evento": "Cámara policial",
        "hora_inicio": "02:10",
        "hora_fin": "02:56",
        "progreso": 83
    },
    {
        "canal": "DiscoveryChannel.ar",
        "evento": "Cámara policial",
        "hora_inicio": "02:10",
        "hora_fin": "02:56",
        "progreso": 83
    },
    {
        "canal": "DiscoveryHomeAndHealth.ar",
        "evento": "Sala de emergencias: historias inéditas",
        "hora_inicio": "02:41",
        "hora_fin": "03:28",
        "progreso": 15
    },
    {
        "canal": "DiscoveryKids.ar",
        "evento": "Jorge, el curioso",
        "hora_inicio": "02:40",
        "hora_fin": "03:02",
        "progreso": 38
    },
    {
        "canal": "DiscoveryTurbo.ar",
        "evento": "Alto octanaje en Las Vegas",
        "hora_inicio": "02:15",
        "hora_fin": "03:07",
        "progreso": 64
    },
    {
        "canal": "DisneyChannel.ar",
        "evento": "Los Green en la gran ciudad",
        "hora_inicio": "02:39",
        "hora_fin": "03:02",
        "progreso": 41
    },
    {
        "canal": "DisneyJunior.ar",
        "evento": "PJ Masks: héroes en pijamas",
        "hora_inicio": "02:30",
        "hora_fin": "02:55",
        "progreso": 73
    },
    {
        "canal": "ElGarageTv.ar",
        "evento": "Top Motor",
        "hora_inicio": "02:30",
        "hora_fin": "03:00",
        "progreso": 61
    },
    {
        "canal": "ElGourmet.ar",
        "evento": "Nardelli al natural",
        "hora_inicio": "02:30",
        "hora_fin": "03:00",
        "progreso": 61
    },
    {
        "canal": "ELNueve.ar",
        "evento": "Telenueve central",
        "hora_inicio": "02:45",
        "hora_fin": "03:30",
        "progreso": 7
    },
    {
        "canal": "ELTrece.ar",
        "evento": "Fin de transmisión",
        "hora_inicio": "01:15",
        "hora_fin": "06:30",
        "progreso": 29
    },
    {
        "canal": "Encuentro.ar",
        "evento": "Universo conurbano",
        "hora_inicio": "02:30",
        "hora_fin": "03:00",
        "progreso": 61
    },
    {
        "canal": "ESPN.ar",
        "evento": "ESPN Mundial",
        "hora_inicio": "02:00",
        "hora_fin": "04:00",
        "progreso": 40
    },
    {
        "canal": "ESPN2.ar",
        "evento": "Alemania vs. Argentina",
        "hora_inicio": "02:00",
        "hora_fin": "03:45",
        "progreso": 46
    },
    {
        "canal": "ESPN3.ar",
        "evento": "Ronda final, Shinnecock Hills Gc, Southampton, NY, USA",
        "hora_inicio": "02:00",
        "hora_fin": "05:00",
        "progreso": 26
    },
    {
        "canal": "ESPN4.ar",
        "evento": "XPEL Grand Prix at Road America, Elkhart Lake, Wisconsin",
        "hora_inicio": "02:00",
        "hora_fin": "04:00",
        "progreso": 40
    },
    {
        "canal": "ESPNExtra.ar",
        "evento": "ESPN Knockout",
        "hora_inicio": "02:00",
        "hora_fin": "04:00",
        "progreso": 40
    },
    {
        "canal": "ESPNSur.ar",
        "evento": "ESPN Mundial",
        "hora_inicio": "22:00",
        "hora_fin": "03:00",
        "progreso": 96
    },
    {
        "canal": "ESPNSur2.ar",
        "evento": "ESPN Knockout",
        "hora_inicio": "01:00",
        "hora_fin": "03:00",
        "progreso": 90
    },
    {
        "canal": "ESPNSur3.ar",
        "evento": "Automovilismo IndyCar Series",
        "hora_inicio": "01:00",
        "hora_fin": "03:00",
        "progreso": 90
    },
    {
        "canal": "ESPNSur4.ar",
        "evento": "ATP Tour Uncovered",
        "hora_inicio": "02:30",
        "hora_fin": "03:00",
        "progreso": 61
    },
    {
        "canal": "EuropaEuropa.ar",
        "evento": "Judy",
        "hora_inicio": "02:10",
        "hora_fin": "04:20",
        "progreso": 29
    },
    {
        "canal": "EWTN.ar",
        "evento": "Santo Rosario - Misterios luminosos",
        "hora_inicio": "02:30",
        "hora_fin": "03:00",
        "progreso": 61
    },
    {
        "canal": "filmAndarts.ar",
        "evento": "Vivaldi y Mozart en el Louvre",
        "hora_inicio": "02:45",
        "hora_fin": "03:50",
        "progreso": 5
    },
    {
        "canal": "FOX Sports",
        "evento": "Estudiantes (LP) (Arg) vs. Ind. Medellín (Col)",
        "hora_inicio": "01:30",
        "hora_fin": "03:30",
        "progreso": 65
    },
    {
        "canal": "FOXSports2.ar",
        "evento": "Cuerpo técnico",
        "hora_inicio": "02:00",
        "hora_fin": "03:00",
        "progreso": 80
    },
    {
        "canal": "FOXSports3.ar",
        "evento": "Rookies Cup y GT3, Fecha 7",
        "hora_inicio": "02:00",
        "hora_fin": "04:00",
        "progreso": 40
    },
    {
        "canal": "FOXSportsConoSur.ar",
        "evento": "Estudiantes (LP) (Arg) vs. Ind. Medellín (Col)",
        "hora_inicio": "01:30",
        "hora_fin": "03:30",
        "progreso": 65
    },
    {
        "canal": "France24enEspanol.ar",
        "evento": "Francia en foco",
        "hora_inicio": "02:40",
        "hora_fin": "02:53",
        "progreso": 64
    },
    {
        "canal": "FX.ar",
        "evento": "Dolor y gloria",
        "hora_inicio": "01:54",
        "hora_fin": "03:45",
        "progreso": 49
    },
    {
        "canal": "GaliciaTV.ar",
        "evento": "Galicia por diante",
        "hora_inicio": "02:00",
        "hora_fin": "03:00",
        "progreso": 80
    },
    {
        "canal": "Golden.ar",
        "evento": "Top Gun, reto a la gloria",
        "hora_inicio": "01:37",
        "hora_fin": "03:39",
        "progreso": 58
    },
    {
        "canal": "GoldenEdge.ar",
        "evento": "Jigsaw: El juego continúa",
        "hora_inicio": "01:21",
        "hora_fin": "02:58",
        "progreso": 90
    },
    {
        "canal": "GolfChannel.ar",
        "evento": "Final Exam",
        "hora_inicio": "02:30",
        "hora_fin": "03:00",
        "progreso": 61
    },
    {
        "canal": "HAPSATV.ar",
        "evento": "Turf en vivo - Palermo, San Isidro y La Plata",
        "hora_inicio": "00:00",
        "hora_fin": "04:00",
        "progreso": 70
    },
    {
        "canal": "HBO.ar",
        "evento": "Drácula: la historia jamás contada",
        "hora_inicio": "02:46",
        "hora_fin": "04:21",
        "progreso": 2
    },
    {
        "canal": "HBO2.ar",
        "evento": "Agente Salt",
        "hora_inicio": "02:31",
        "hora_fin": "04:16",
        "progreso": 16
    },
    {
        "canal": "HBOFamily.ar",
        "evento": "El cazador y la reina de hielo",
        "hora_inicio": "01:40",
        "hora_fin": "03:36",
        "progreso": 58
    },
    {
        "canal": "HBOMundi.ar",
        "evento": "Papi",
        "hora_inicio": "02:30",
        "hora_fin": "04:14",
        "progreso": 17
    },
    {
        "canal": "HBOOeste.ar",
        "evento": "Te van a matar",
        "hora_inicio": "01:00",
        "hora_fin": "02:53",
        "progreso": 95
    },
    {
        "canal": "HBOPlus(Panamericano).ar",
        "evento": "¡Shazam! La furia de los dioses",
        "hora_inicio": "01:00",
        "hora_fin": "03:15",
        "progreso": 80
    },
    {
        "canal": "HBOPlusEste.ar",
        "evento": "¡Shazam! La furia de los dioses",
        "hora_inicio": "01:00",
        "hora_fin": "03:15",
        "progreso": 80
    },
    {
        "canal": "HBOPop.ar",
        "evento": "Una esposa de mentira",
        "hora_inicio": "01:55",
        "hora_fin": "03:55",
        "progreso": 44
    },
    {
        "canal": "HBOSignature.ar",
        "evento": "Revueltas en Baltimore",
        "hora_inicio": "02:13",
        "hora_fin": "03:53",
        "progreso": 35
    },
    {
        "canal": "HBOXtreme(Panamericano).ar",
        "evento": "No hables con extraños",
        "hora_inicio": "02:44",
        "hora_fin": "04:37",
        "progreso": 3
    },
    {
        "canal": "HBOXtreme.ar",
        "evento": "No hables con extraños",
        "hora_inicio": "02:44",
        "hora_fin": "04:37",
        "progreso": 3
    },
    {
        "canal": "HGTV.ar",
        "evento": "¿Por qué compré esta casa?",
        "hora_inicio": "02:43",
        "hora_fin": "03:27",
        "progreso": 12
    },
    {
        "canal": "HispanTV.ar",
        "evento": "Detrás de la razón",
        "hora_inicio": "02:30",
        "hora_fin": "03:00",
        "progreso": 61
    },
    {
        "canal": "History.ar",
        "evento": "Maravillas siniestras",
        "hora_inicio": "02:24",
        "hora_fin": "03:06",
        "progreso": 58
    },
    {
        "canal": "History2.ar",
        "evento": "Lugares misteriosos",
        "hora_inicio": "02:35",
        "hora_fin": "03:34",
        "progreso": 22
    },
    {
        "canal": "HolaTV.ar",
        "evento": "Valeria Mazza: un sueño dorado",
        "hora_inicio": "02:00",
        "hora_fin": "03:00",
        "progreso": 80
    },
    {
        "canal": "HTV.ar",
        "evento": "HTV",
        "hora_inicio": "01:00",
        "hora_fin": "09:00",
        "progreso": 22
    },
    {
        "canal": "InvestigationDiscovery.ar",
        "evento": "La casa del mal",
        "hora_inicio": "02:12",
        "hora_fin": "02:59",
        "progreso": 77
    },
    {
        "canal": "LasEstrellas.ar",
        "evento": "Doménica Montero",
        "hora_inicio": "23:10",
        "hora_fin": "03:00",
        "progreso": 94
    },
    {
        "canal": "LN+.ar",
        "evento": "+Nación",
        "hora_inicio": "01:00",
        "hora_fin": "03:00",
        "progreso": 90
    },
    {
        "canal": "MasChic.ar",
        "evento": "Lodge 49",
        "hora_inicio": "01:55",
        "hora_fin": "02:55",
        "progreso": 89
    },
    {
        "canal": "Metro.ar",
        "evento": "BF Lifting y refresh",
        "hora_inicio": "02:30",
        "hora_fin": "03:00",
        "progreso": 61
    },
    {
        "canal": "MTV.ar",
        "evento": "Ridiculousness",
        "hora_inicio": "02:30",
        "hora_fin": "02:50",
        "progreso": 92
    },
    {
        "canal": "Musictop.ar",
        "evento": "MusicTop",
        "hora_inicio": "02:00",
        "hora_fin": "03:00",
        "progreso": 80
    },
    {
        "canal": "NationalGeographic.ar",
        "evento": "Mayday: catástrofes aéreas",
        "hora_inicio": "02:06",
        "hora_fin": "02:51",
        "progreso": 94
    },
    {
        "canal": "NBATV.ar",
        "evento": "2026 NBA Draft Review",
        "hora_inicio": "02:00",
        "hora_fin": "03:00",
        "progreso": 80
    },
    {
        "canal": "NetTV.ar",
        "evento": "El valor de tus joyas",
        "hora_inicio": "02:00",
        "hora_fin": "05:00",
        "progreso": 26
    },
    {
        "canal": "NickJr..ar",
        "evento": "Barbapapá",
        "hora_inicio": "02:35",
        "hora_fin": "02:55",
        "progreso": 67
    },
    {
        "canal": "Pakapaka.ar",
        "evento": "Puerto papel",
        "hora_inicio": "02:45",
        "hora_fin": "03:15",
        "progreso": 11
    },
    {
        "canal": "Pasiones.ar",
        "evento": "Pantanal",
        "hora_inicio": "02:00",
        "hora_fin": "03:00",
        "progreso": 80
    },
    {
        "canal": "PenthouseGold.ar",
        "evento": "Acábame, profe",
        "hora_inicio": "01:55",
        "hora_fin": "03:50",
        "progreso": 46
    },
    {
        "canal": "Playboy.ar",
        "evento": "Blonde Obsession",
        "hora_inicio": "02:26",
        "hora_fin": "02:50",
        "progreso": 93
    },
    {
        "canal": "Quiero.ar",
        "evento": "Lo que quiero",
        "hora_inicio": "02:30",
        "hora_fin": "04:30",
        "progreso": 15
    },
    {
        "canal": "RaiItalia.ar",
        "evento": "Unomattina News",
        "hora_inicio": "02:15",
        "hora_fin": "03:00",
        "progreso": 74
    },
    {
        "canal": "RussiaToday.ar",
        "evento": "Ahí les va",
        "hora_inicio": "02:30",
        "hora_fin": "03:00",
        "progreso": 61
    },
    {
        "canal": "Sony.ar",
        "evento": "Volver al futuro III",
        "hora_inicio": "00:05",
        "hora_fin": "03:10",
        "progreso": 88
    },
    {
        "canal": "Space.ar",
        "evento": "Annabelle vuelve a casa",
        "hora_inicio": "01:56",
        "hora_fin": "03:41",
        "progreso": 49
    },
    {
        "canal": "StarChannel.ar",
        "evento": "American Horror Stories",
        "hora_inicio": "02:06",
        "hora_fin": "02:50",
        "progreso": 96
    },
    {
        "canal": "StudioUniversal.ar",
        "evento": "Una sombra en la nube",
        "hora_inicio": "01:20",
        "hora_fin": "02:55",
        "progreso": 93
    },
    {
        "canal": "TCM.ar",
        "evento": "Motín a bordo",
        "hora_inicio": "02:28",
        "hora_fin": "05:34",
        "progreso": 10
    },
    {
        "canal": "TECtv.ar",
        "evento": "TecTV",
        "hora_inicio": "00:00",
        "hora_fin": "04:00",
        "progreso": 70
    },
    {
        "canal": "Telediario.ar",
        "evento": "Resumen de noticias",
        "hora_inicio": "02:00",
        "hora_fin": "04:00",
        "progreso": 40
    },
    {
        "canal": "Telefe.ar",
        "evento": "Escocia vs. Brasil",
        "hora_inicio": "01:30",
        "hora_fin": "03:45",
        "progreso": 58
    },
    {
        "canal": "TelefeCordoba.ar",
        "evento": "100 días para enamorarse",
        "hora_inicio": "02:00",
        "hora_fin": "03:00",
        "progreso": 80
    },
    {
        "canal": "TelefeRosario.ar",
        "evento": "Telefe noticias",
        "hora_inicio": "02:00",
        "hora_fin": "03:30",
        "progreso": 53
    },
    {
        "canal": "TelefeSantaFe.ar",
        "evento": "Noticiero Santa Fe - 2º Edición",
        "hora_inicio": "02:15",
        "hora_fin": "03:45",
        "progreso": 37
    },
    {
        "canal": "Telehit.ar",
        "evento": "Horoscopía",
        "hora_inicio": "02:00",
        "hora_fin": "03:00",
        "progreso": 80
    },
    {
        "canal": "Telemax.ar",
        "evento": "Documentales de interés general",
        "hora_inicio": "00:00",
        "hora_fin": "06:00",
        "progreso": 46
    },
    {
        "canal": "teleSUR.ar",
        "evento": "Telesur Noticias",
        "hora_inicio": "02:30",
        "hora_fin": "03:00",
        "progreso": 61
    },
    {
        "canal": "TelevisionPublica.ar",
        "evento": "Fin de transmisión",
        "hora_inicio": "00:30",
        "hora_fin": "06:45",
        "progreso": 36
    },
    {
        "canal": "TierraMiaTV.ar",
        "evento": "TierraMia TV",
        "hora_inicio": "02:00",
        "hora_fin": "03:00",
        "progreso": 80
    },
    {
        "canal": "TLC.ar",
        "evento": "Amor extranjero",
        "hora_inicio": "02:24",
        "hora_fin": "03:08",
        "progreso": 55
    },
    {
        "canal": "TLNovelas.ar",
        "evento": "La rosa de Guadalupe",
        "hora_inicio": "02:00",
        "hora_fin": "02:50",
        "progreso": 96
    },
    {
        "canal": "TN.ar",
        "evento": "Re despiertos",
        "hora_inicio": "01:00",
        "hora_fin": "05:00",
        "progreso": 45
    },
    {
        "canal": "TNT.ar",
        "evento": "La liga de la justicia de Zack Snyder",
        "hora_inicio": "02:10",
        "hora_fin": "06:00",
        "progreso": 16
    },
    {
        "canal": "TNTSeries.ar",
        "evento": "La ley y el orden: UVE",
        "hora_inicio": "02:21",
        "hora_fin": "03:04",
        "progreso": 63
    },
    {
        "canal": "Tooncast.ar",
        "evento": "Don Gato y su pandilla",
        "hora_inicio": "02:32",
        "hora_fin": "02:57",
        "progreso": 65
    },
    {
        "canal": "TurismoVisionArgentina.ar",
        "evento": "Turismo Visión Argentina",
        "hora_inicio": "00:00",
        "hora_fin": "03:00",
        "progreso": 93
    },
    {
        "canal": "TV5.ar",
        "evento": "C dans l'air",
        "hora_inicio": "02:30",
        "hora_fin": "03:37",
        "progreso": 27
    },
    {
        "canal": "TVCiudad.ar",
        "evento": "Lado B",
        "hora_inicio": "02:00",
        "hora_fin": "04:00",
        "progreso": 40
    },
    {
        "canal": "TVE.ar",
        "evento": "Telediario matinal",
        "hora_inicio": "02:30",
        "hora_fin": "02:50",
        "progreso": 92
    },
    {
        "canal": "TVGlobo.ar",
        "evento": "Coração acelerado",
        "hora_inicio": "02:20",
        "hora_fin": "03:00",
        "progreso": 71
    },
    {
        "canal": "TVNacionalUruguay.ar",
        "evento": "Escocia vs. Brasil",
        "hora_inicio": "01:30",
        "hora_fin": "03:30",
        "progreso": 65
    },
    {
        "canal": "TVNCHILE.ar",
        "evento": "El mediodía",
        "hora_inicio": "02:30",
        "hora_fin": "04:00",
        "progreso": 20
    },
    {
        "canal": "TVPublica.ar",
        "evento": "Fin de transmisión",
        "hora_inicio": "00:30",
        "hora_fin": "06:45",
        "progreso": 36
    },
    {
        "canal": "TyCSports.ar",
        "evento": "Copa Mundial de la FIFA 26",
        "hora_inicio": "02:00",
        "hora_fin": "03:00",
        "progreso": 80
    },
    {
        "canal": "TyCSports2.ar",
        "evento": "TyC Sports 2",
        "hora_inicio": "00:00",
        "hora_fin": "12:00",
        "progreso": 23
    },
    {
        "canal": "UniversalTV.ar",
        "evento": "Chicago Fire",
        "hora_inicio": "02:00",
        "hora_fin": "02:50",
        "progreso": 96
    },
    {
        "canal": "UruguayNaturalTV.ar",
        "evento": "Uruguay Natural TV",
        "hora_inicio": "00:00",
        "hora_fin": "04:00",
        "progreso": 70
    },
    {
        "canal": "Venus.ar",
        "evento": "100% Pornstars",
        "hora_inicio": "02:13",
        "hora_fin": "03:39",
        "progreso": 41
    },
    {
        "canal": "Volver.ar",
        "evento": "País cerrado, teatro abierto",
        "hora_inicio": "01:30",
        "hora_fin": "03:00",
        "progreso": 87
    },
    {
        "canal": "VTV.ar",
        "evento": "Buscadores",
        "hora_inicio": "01:00",
        "hora_fin": "03:00",
        "progreso": 90
    },
    {
        "canal": "WarnerChannel.ar",
        "evento": "Mortal Kombat",
        "hora_inicio": "00:58",
        "hora_fin": "02:53",
        "progreso": 96
    },
    {
        "canal": "ZooMoo.ar",
        "evento": "Jelly Jamm",
        "hora_inicio": "02:45",
        "hora_fin": "03:00",
        "progreso": 22
    }
]