[
    {
        "canal": "24/7CanaldeNoticias.ar",
        "evento": "Así estamos",
        "hora_inicio": "10:00",
        "hora_fin": "13:00",
        "progreso": 77
    },
    {
        "canal": "A24.ar",
        "evento": "Buen día A24",
        "hora_inicio": "10:00",
        "hora_fin": "13:00",
        "progreso": 77
    },
    {
        "canal": "AMC.ar",
        "evento": "Maestras del engaño",
        "hora_inicio": "12:00",
        "hora_fin": "13:50",
        "progreso": 17
    },
    {
        "canal": "AmericaSports.ar",
        "evento": "Alma de turf",
        "hora_inicio": "12:00",
        "hora_fin": "13:00",
        "progreso": 32
    },
    {
        "canal": "AmericaTV.ar",
        "evento": "Lape Club social informativo",
        "hora_inicio": "12:00",
        "hora_fin": "13:00",
        "progreso": 32
    },
    {
        "canal": "AnimalPlanet.ar",
        "evento": "Guaridas con estilo",
        "hora_inicio": "11:58",
        "hora_fin": "12:50",
        "progreso": 41
    },
    {
        "canal": "ArgentinisimaSatelital.ar",
        "evento": "Argentinisima satelital",
        "hora_inicio": "12:00",
        "hora_fin": "15:00",
        "progreso": 10
    },
    {
        "canal": "Atreseries.ar",
        "evento": "Pop Up: Aquí no hay quien viva",
        "hora_inicio": "10:30",
        "hora_fin": "15:14",
        "progreso": 38
    },
    {
        "canal": "AXN.ar",
        "evento": "NCIS: New Orleans",
        "hora_inicio": "11:50",
        "hora_fin": "12:44",
        "progreso": 54
    },
    {
        "canal": "BabyTV.ar",
        "evento": "Giggle Wiggle",
        "hora_inicio": "12:00",
        "hora_fin": "12:30",
        "progreso": 64
    },
    {
        "canal": "Bloomberg.ar",
        "evento": "Bloomberg Technology",
        "hora_inicio": "12:00",
        "hora_fin": "13:00",
        "progreso": 32
    },
    {
        "canal": "C5N.ar",
        "evento": "La mañana",
        "hora_inicio": "10:00",
        "hora_fin": "13:00",
        "progreso": 77
    },
    {
        "canal": "Canal21.ar",
        "evento": "Poliedro Latinoamericano",
        "hora_inicio": "10:30",
        "hora_fin": "13:00",
        "progreso": 72
    },
    {
        "canal": "Canal26.ar",
        "evento": "Vivo al mediodía",
        "hora_inicio": "12:00",
        "hora_fin": "14:00",
        "progreso": 16
    },
    {
        "canal": "CanalDeLaCiudad.ar",
        "evento": "N 12.30",
        "hora_inicio": "12:00",
        "hora_fin": "14:00",
        "progreso": 16
    },
    {
        "canal": "CanalDeLaMusica.ar",
        "evento": "CM Latino",
        "hora_inicio": "12:00",
        "hora_fin": "12:30",
        "progreso": 64
    },
    {
        "canal": "CanalRural.ar",
        "evento": "A corral",
        "hora_inicio": "12:00",
        "hora_fin": "12:30",
        "progreso": 64
    },
    {
        "canal": "CartoonNetwork.ar",
        "evento": "Los Jóvenes Titanes en acción",
        "hora_inicio": "12:18",
        "hora_fin": "12:29",
        "progreso": 13
    },
    {
        "canal": "CineAr.ar",
        "evento": "Carlos Gesell, mi padre",
        "hora_inicio": "12:00",
        "hora_fin": "14:00",
        "progreso": 16
    },
    {
        "canal": "Cinecanal.ar",
        "evento": "Historias cruzadas",
        "hora_inicio": "11:47",
        "hora_fin": "14:53",
        "progreso": 17
    },
    {
        "canal": "Cinelatino.ar",
        "evento": "Marcelo",
        "hora_inicio": "11:15",
        "hora_fin": "13:10",
        "progreso": 56
    },
    {
        "canal": "Cinemax(Sur).ar",
        "evento": "Los ángeles de Charlie: Al límite",
        "hora_inicio": "11:21",
        "hora_fin": "13:22",
        "progreso": 48
    },
    {
        "canal": "Cinemax.ar",
        "evento": "Los pingüinos de Madagascar",
        "hora_inicio": "11:59",
        "hora_fin": "13:28",
        "progreso": 23
    },
    {
        "canal": "CiudadMagazine.ar",
        "evento": "Mshow",
        "hora_inicio": "12:00",
        "hora_fin": "13:00",
        "progreso": 32
    },
    {
        "canal": "CN23.ar",
        "evento": "CN 23",
        "hora_inicio": "12:00",
        "hora_fin": "13:00",
        "progreso": 32
    },
    {
        "canal": "CNNenEspanol.ar",
        "evento": "Deportes CNN",
        "hora_inicio": "12:00",
        "hora_fin": "12:30",
        "progreso": 64
    },
    {
        "canal": "ComedyCentral.ar",
        "evento": "El rey del barrio",
        "hora_inicio": "12:05",
        "hora_fin": "12:25",
        "progreso": 72
    },
    {
        "canal": "ConexionEducativa.ar",
        "evento": "Conexión educativa",
        "hora_inicio": "12:00",
        "hora_fin": "15:00",
        "progreso": 10
    },
    {
        "canal": "ConstruirTV.ar",
        "evento": "Un lugar llamado México",
        "hora_inicio": "12:00",
        "hora_fin": "12:30",
        "progreso": 64
    },
    {
        "canal": "CronicaTV.ar",
        "evento": "Siempre noticias",
        "hora_inicio": "12:00",
        "hora_fin": "14:00",
        "progreso": 16
    },
    {
        "canal": "Discovery.ar",
        "evento": "Supervivencia al desnudo",
        "hora_inicio": "11:48",
        "hora_fin": "12:39",
        "progreso": 61
    },
    {
        "canal": "DiscoveryChannel.ar",
        "evento": "Supervivencia al desnudo",
        "hora_inicio": "11:48",
        "hora_fin": "12:39",
        "progreso": 61
    },
    {
        "canal": "DiscoveryHomeAndHealth.ar",
        "evento": "Dra. Sandra Lee: especialista en piel",
        "hora_inicio": "11:54",
        "hora_fin": "12:40",
        "progreso": 55
    },
    {
        "canal": "DiscoveryKids.ar",
        "evento": "Mini Beat Power Rockers",
        "hora_inicio": "12:04",
        "hora_fin": "12:31",
        "progreso": 57
    },
    {
        "canal": "DiscoveryTurbo.ar",
        "evento": "Misfit Garage",
        "hora_inicio": "12:14",
        "hora_fin": "13:06",
        "progreso": 10
    },
    {
        "canal": "DisneyChannel.ar",
        "evento": "Phineas y Ferb",
        "hora_inicio": "11:59",
        "hora_fin": "12:29",
        "progreso": 68
    },
    {
        "canal": "DisneyJunior.ar",
        "evento": "Supergatitos",
        "hora_inicio": "12:03",
        "hora_fin": "12:33",
        "progreso": 54
    },
    {
        "canal": "ElGarageTv.ar",
        "evento": "Adventure Trail",
        "hora_inicio": "12:00",
        "hora_fin": "12:30",
        "progreso": 64
    },
    {
        "canal": "ElGourmet.ar",
        "evento": "Productos artesanos",
        "hora_inicio": "12:00",
        "hora_fin": "12:30",
        "progreso": 64
    },
    {
        "canal": "ELNueve.ar",
        "evento": "Telenueve al mediodía",
        "hora_inicio": "12:00",
        "hora_fin": "13:30",
        "progreso": 21
    },
    {
        "canal": "ELTrece.ar",
        "evento": "Puro show",
        "hora_inicio": "10:30",
        "hora_fin": "12:30",
        "progreso": 91
    },
    {
        "canal": "Encuentro.ar",
        "evento": "Haylli, una memoria revelada",
        "hora_inicio": "12:00",
        "hora_fin": "12:30",
        "progreso": 64
    },
    {
        "canal": "ESPN.ar",
        "evento": "ESPN Mundial",
        "hora_inicio": "11:00",
        "hora_fin": "15:00",
        "progreso": 33
    },
    {
        "canal": "ESPN2.ar",
        "evento": "Primera ronda, All England Lawn Tennis & Croquet Club, Wimbledon, England",
        "hora_inicio": "07:00",
        "hora_fin": "17:00",
        "progreso": 53
    },
    {
        "canal": "ESPN3.ar",
        "evento": "Primera ronda, All England Lawn Tennis & Croquet Club, Wimbledon, England",
        "hora_inicio": "07:00",
        "hora_fin": "17:00",
        "progreso": 53
    },
    {
        "canal": "ESPN4.ar",
        "evento": "Lomas vs. San Fernando",
        "hora_inicio": "10:45",
        "hora_fin": "12:30",
        "progreso": 89
    },
    {
        "canal": "ESPNSur.ar",
        "evento": "ESPN Mundial",
        "hora_inicio": "12:00",
        "hora_fin": "16:00",
        "progreso": 8
    },
    {
        "canal": "ESPNSur2.ar",
        "evento": "Campeonato de Wimbledon 2026",
        "hora_inicio": "08:00",
        "hora_fin": "16:00",
        "progreso": 54
    },
    {
        "canal": "ESPNSur3.ar",
        "evento": "Campeonato de Wimbledon 2026",
        "hora_inicio": "08:00",
        "hora_fin": "16:00",
        "progreso": 54
    },
    {
        "canal": "ESPNSur4.ar",
        "evento": "Hockey sobre césped de Argentina",
        "hora_inicio": "11:45",
        "hora_fin": "13:30",
        "progreso": 32
    },
    {
        "canal": "EuropaEuropa.ar",
        "evento": "El alemán",
        "hora_inicio": "11:30",
        "hora_fin": "12:25",
        "progreso": 89
    },
    {
        "canal": "EWTN.ar",
        "evento": "Informe Pro Vida",
        "hora_inicio": "12:00",
        "hora_fin": "12:30",
        "progreso": 64
    },
    {
        "canal": "filmAndarts.ar",
        "evento": "Open at Night",
        "hora_inicio": "11:05",
        "hora_fin": "13:00",
        "progreso": 64
    },
    {
        "canal": "FOX Sports",
        "evento": "Gran Premio de Austria, Red Bull Ring",
        "hora_inicio": "11:00",
        "hora_fin": "13:00",
        "progreso": 66
    },
    {
        "canal": "FOXSports2.ar",
        "evento": "Final",
        "hora_inicio": "11:30",
        "hora_fin": "12:30",
        "progreso": 82
    },
    {
        "canal": "FOXSports3.ar",
        "evento": "Circuito ROTAX",
        "hora_inicio": "12:00",
        "hora_fin": "13:00",
        "progreso": 32
    },
    {
        "canal": "FOXSportsConoSur.ar",
        "evento": "Gran Premio de Austria, Red Bull Ring",
        "hora_inicio": "11:00",
        "hora_fin": "13:00",
        "progreso": 66
    },
    {
        "canal": "France24enEspanol.ar",
        "evento": "Revista de prensa",
        "hora_inicio": "12:15",
        "hora_fin": "12:20",
        "progreso": 89
    },
    {
        "canal": "FX.ar",
        "evento": "Queen y Slim: los fugitivos",
        "hora_inicio": "10:21",
        "hora_fin": "13:03",
        "progreso": 73
    },
    {
        "canal": "GaliciaTV.ar",
        "evento": "En compañía de Loli",
        "hora_inicio": "11:00",
        "hora_fin": "14:00",
        "progreso": 44
    },
    {
        "canal": "Golden.ar",
        "evento": "El candidato honesto",
        "hora_inicio": "10:37",
        "hora_fin": "12:20",
        "progreso": 99
    },
    {
        "canal": "GoldenEdge.ar",
        "evento": "Volver al futuro",
        "hora_inicio": "11:57",
        "hora_fin": "14:01",
        "progreso": 18
    },
    {
        "canal": "GolfChannel.ar",
        "evento": "Golf Channel",
        "hora_inicio": "07:00",
        "hora_fin": "13:00",
        "progreso": 88
    },
    {
        "canal": "HAPSATV.ar",
        "evento": "Turf en vivo - Palermo, San Isidro y La Plata",
        "hora_inicio": "12:00",
        "hora_fin": "16:00",
        "progreso": 8
    },
    {
        "canal": "HBO.ar",
        "evento": "Interestelar",
        "hora_inicio": "10:35",
        "hora_fin": "13:30",
        "progreso": 59
    },
    {
        "canal": "HBO2.ar",
        "evento": "Furiosa: de la saga Mad Max",
        "hora_inicio": "11:44",
        "hora_fin": "14:20",
        "progreso": 22
    },
    {
        "canal": "HBOFamily.ar",
        "evento": "Los Pitufos",
        "hora_inicio": "10:50",
        "hora_fin": "12:35",
        "progreso": 85
    },
    {
        "canal": "HBOMundi.ar",
        "evento": "Cuestión de honor",
        "hora_inicio": "12:09",
        "hora_fin": "14:35",
        "progreso": 7
    },
    {
        "canal": "HBOOeste.ar",
        "evento": "Quiero matar a mi jefe",
        "hora_inicio": "11:07",
        "hora_fin": "12:52",
        "progreso": 69
    },
    {
        "canal": "HBOPlus(Panamericano).ar",
        "evento": "Mickey 17",
        "hora_inicio": "11:10",
        "hora_fin": "13:35",
        "progreso": 47
    },
    {
        "canal": "HBOPlusEste.ar",
        "evento": "Mickey 17",
        "hora_inicio": "11:10",
        "hora_fin": "13:35",
        "progreso": 47
    },
    {
        "canal": "HBOPop.ar",
        "evento": "Karate Kid 4",
        "hora_inicio": "11:10",
        "hora_fin": "12:59",
        "progreso": 63
    },
    {
        "canal": "HBOSignature.ar",
        "evento": "Super/Man - La historia de Christopher Reeve",
        "hora_inicio": "11:43",
        "hora_fin": "13:37",
        "progreso": 32
    },
    {
        "canal": "HBOXtreme(Panamericano).ar",
        "evento": "Oblivion: el tiempo del olvido",
        "hora_inicio": "11:19",
        "hora_fin": "13:31",
        "progreso": 45
    },
    {
        "canal": "HBOXtreme.ar",
        "evento": "Oblivion: el tiempo del olvido",
        "hora_inicio": "11:19",
        "hora_fin": "13:31",
        "progreso": 45
    },
    {
        "canal": "HGTV.ar",
        "evento": "¿Por qué compré esta casa?",
        "hora_inicio": "11:48",
        "hora_fin": "12:35",
        "progreso": 66
    },
    {
        "canal": "HispanTV.ar",
        "evento": "Brecha económica",
        "hora_inicio": "12:00",
        "hora_fin": "12:30",
        "progreso": 64
    },
    {
        "canal": "History.ar",
        "evento": "El secreto de Skinwalker",
        "hora_inicio": "11:54",
        "hora_fin": "12:36",
        "progreso": 60
    },
    {
        "canal": "History2.ar",
        "evento": "Persiguiendo a Hitler",
        "hora_inicio": "12:12",
        "hora_fin": "13:02",
        "progreso": 14
    },
    {
        "canal": "HolaTV.ar",
        "evento": "Las reinas del Shopping",
        "hora_inicio": "12:00",
        "hora_fin": "13:00",
        "progreso": 32
    },
    {
        "canal": "HTV.ar",
        "evento": "HTV",
        "hora_inicio": "09:00",
        "hora_fin": "14:00",
        "progreso": 66
    },
    {
        "canal": "InvestigationDiscovery.ar",
        "evento": "Demonios de Hollywood",
        "hora_inicio": "11:19",
        "hora_fin": "12:53",
        "progreso": 64
    },
    {
        "canal": "LasEstrellas.ar",
        "evento": "Como dice el dicho",
        "hora_inicio": "12:00",
        "hora_fin": "12:50",
        "progreso": 38
    },
    {
        "canal": "LN+.ar",
        "evento": "+Noticias",
        "hora_inicio": "12:00",
        "hora_fin": "14:00",
        "progreso": 16
    },
    {
        "canal": "MasChic.ar",
        "evento": "Planet Action",
        "hora_inicio": "12:00",
        "hora_fin": "12:30",
        "progreso": 64
    },
    {
        "canal": "Metro.ar",
        "evento": "En forma - Tecnología estética",
        "hora_inicio": "12:00",
        "hora_fin": "13:00",
        "progreso": 32
    },
    {
        "canal": "MTV.ar",
        "evento": "Teen Mom",
        "hora_inicio": "12:00",
        "hora_fin": "12:40",
        "progreso": 48
    },
    {
        "canal": "Musictop.ar",
        "evento": "MusicTop",
        "hora_inicio": "12:00",
        "hora_fin": "13:00",
        "progreso": 32
    },
    {
        "canal": "NationalGeographic.ar",
        "evento": "Gordon Ramsay: sabores extremos",
        "hora_inicio": "11:44",
        "hora_fin": "12:44",
        "progreso": 59
    },
    {
        "canal": "NBATV.ar",
        "evento": "NBA Draft edition",
        "hora_inicio": "12:00",
        "hora_fin": "13:00",
        "progreso": 32
    },
    {
        "canal": "NetTV.ar",
        "evento": "Modo Fontevecchia",
        "hora_inicio": "10:00",
        "hora_fin": "13:00",
        "progreso": 77
    },
    {
        "canal": "NickJr..ar",
        "evento": "Tim Rex en el espacio",
        "hora_inicio": "12:10",
        "hora_fin": "12:30",
        "progreso": 47
    },
    {
        "canal": "Pakapaka.ar",
        "evento": "La orquestita",
        "hora_inicio": "12:15",
        "hora_fin": "12:30",
        "progreso": 29
    },
    {
        "canal": "Pasiones.ar",
        "evento": "Buscando la felicidad",
        "hora_inicio": "12:00",
        "hora_fin": "13:00",
        "progreso": 32
    },
    {
        "canal": "PenthouseGold.ar",
        "evento": "Acábame, profe",
        "hora_inicio": "10:48",
        "hora_fin": "12:44",
        "progreso": 78
    },
    {
        "canal": "Playboy.ar",
        "evento": "Boss Seduction",
        "hora_inicio": "11:03",
        "hora_fin": "12:40",
        "progreso": 78
    },
    {
        "canal": "Quiero.ar",
        "evento": "En alta",
        "hora_inicio": "11:00",
        "hora_fin": "13:00",
        "progreso": 66
    },
    {
        "canal": "RaiItalia.ar",
        "evento": "La vita in diretta",
        "hora_inicio": "11:15",
        "hora_fin": "13:45",
        "progreso": 42
    },
    {
        "canal": "RussiaToday.ar",
        "evento": "Noticias",
        "hora_inicio": "12:00",
        "hora_fin": "12:30",
        "progreso": 64
    },
    {
        "canal": "Sony.ar",
        "evento": "La niñera",
        "hora_inicio": "11:05",
        "hora_fin": "13:05",
        "progreso": 62
    },
    {
        "canal": "Space.ar",
        "evento": "Hancock",
        "hora_inicio": "11:02",
        "hora_fin": "12:43",
        "progreso": 76
    },
    {
        "canal": "StarChannel.ar",
        "evento": "El día que la Tierra se detuvo",
        "hora_inicio": "11:31",
        "hora_fin": "13:45",
        "progreso": 36
    },
    {
        "canal": "StudioUniversal.ar",
        "evento": "Laberinto",
        "hora_inicio": "11:05",
        "hora_fin": "12:55",
        "progreso": 67
    },
    {
        "canal": "TCM.ar",
        "evento": "Madame Bovary",
        "hora_inicio": "11:54",
        "hora_fin": "13:54",
        "progreso": 21
    },
    {
        "canal": "TECtv.ar",
        "evento": "TecTV",
        "hora_inicio": "12:00",
        "hora_fin": "16:00",
        "progreso": 8
    },
    {
        "canal": "Telediario.ar",
        "evento": "Sabores con humor",
        "hora_inicio": "12:00",
        "hora_fin": "13:00",
        "progreso": 32
    },
    {
        "canal": "Telefe.ar",
        "evento": "Flash Mundial",
        "hora_inicio": "12:00",
        "hora_fin": "12:45",
        "progreso": 43
    },
    {
        "canal": "TelefeCordoba.ar",
        "evento": "Telefe noticias - 1ra edición",
        "hora_inicio": "11:30",
        "hora_fin": "12:50",
        "progreso": 61
    },
    {
        "canal": "TelefeRosario.ar",
        "evento": "El noticiero de la gente",
        "hora_inicio": "11:10",
        "hora_fin": "13:00",
        "progreso": 63
    },
    {
        "canal": "TelefeSantaFe.ar",
        "evento": "Telefe noticias",
        "hora_inicio": "12:00",
        "hora_fin": "12:45",
        "progreso": 43
    },
    {
        "canal": "Telehit.ar",
        "evento": "Rainbowlist",
        "hora_inicio": "12:00",
        "hora_fin": "13:00",
        "progreso": 32
    },
    {
        "canal": "Telemax.ar",
        "evento": "Tiempo de pesca",
        "hora_inicio": "12:00",
        "hora_fin": "13:00",
        "progreso": 32
    },
    {
        "canal": "teleSUR.ar",
        "evento": "Deportes Telesur",
        "hora_inicio": "12:05",
        "hora_fin": "12:30",
        "progreso": 57
    },
    {
        "canal": "TelevisionPublica.ar",
        "evento": "TVP Noticias",
        "hora_inicio": "12:00",
        "hora_fin": "13:30",
        "progreso": 21
    },
    {
        "canal": "TierraMiaTV.ar",
        "evento": "TierraMia TV",
        "hora_inicio": "12:00",
        "hora_fin": "13:00",
        "progreso": 32
    },
    {
        "canal": "TLC.ar",
        "evento": "De tal madre, tal astilla",
        "hora_inicio": "11:34",
        "hora_fin": "12:21",
        "progreso": 96
    },
    {
        "canal": "TLNovelas.ar",
        "evento": "Amarte es mi pecado",
        "hora_inicio": "12:15",
        "hora_fin": "13:55",
        "progreso": 4
    },
    {
        "canal": "TN.ar",
        "evento": "TN de 10 a 13",
        "hora_inicio": "10:00",
        "hora_fin": "13:00",
        "progreso": 77
    },
    {
        "canal": "TNT.ar",
        "evento": "El cazador y la reina de hielo",
        "hora_inicio": "12:14",
        "hora_fin": "14:14",
        "progreso": 4
    },
    {
        "canal": "TNTSeries.ar",
        "evento": "CSI",
        "hora_inicio": "12:15",
        "hora_fin": "13:04",
        "progreso": 9
    },
    {
        "canal": "Tooncast.ar",
        "evento": "Los pequeños Looney Tunes",
        "hora_inicio": "12:14",
        "hora_fin": "12:24",
        "progreso": 54
    },
    {
        "canal": "TurismoVisionArgentina.ar",
        "evento": "Turismo Visión Argentina",
        "hora_inicio": "12:00",
        "hora_fin": "15:00",
        "progreso": 10
    },
    {
        "canal": "TV5.ar",
        "evento": "La cuisine d'Isabelle et Ricardo",
        "hora_inicio": "12:15",
        "hora_fin": "12:45",
        "progreso": 14
    },
    {
        "canal": "TVCiudad.ar",
        "evento": "Lado B",
        "hora_inicio": "12:00",
        "hora_fin": "13:00",
        "progreso": 32
    },
    {
        "canal": "TVE.ar",
        "evento": "Directo al grano",
        "hora_inicio": "10:55",
        "hora_fin": "13:35",
        "progreso": 52
    },
    {
        "canal": "TVGlobo.ar",
        "evento": "Mais você",
        "hora_inicio": "11:55",
        "hora_fin": "13:00",
        "progreso": 37
    },
    {
        "canal": "TVNacionalUruguay.ar",
        "evento": "Canal 5 noticias",
        "hora_inicio": "12:00",
        "hora_fin": "13:00",
        "progreso": 32
    },
    {
        "canal": "TVNCHILE.ar",
        "evento": "El mediodía",
        "hora_inicio": "11:45",
        "hora_fin": "14:00",
        "progreso": 25
    },
    {
        "canal": "TVPublica.ar",
        "evento": "TVP Noticias",
        "hora_inicio": "12:00",
        "hora_fin": "13:30",
        "progreso": 21
    },
    {
        "canal": "TyCSports.ar",
        "evento": "El análisis de Argentina y la previa de Brasil vs. Japón",
        "hora_inicio": "12:00",
        "hora_fin": "14:00",
        "progreso": 16
    },
    {
        "canal": "TyCSports2.ar",
        "evento": "TyC Sports 2",
        "hora_inicio": "12:00",
        "hora_fin": "19:00",
        "progreso": 4
    },
    {
        "canal": "UniversalTV.ar",
        "evento": "La ley y el orden: UVE",
        "hora_inicio": "11:50",
        "hora_fin": "12:40",
        "progreso": 58
    },
    {
        "canal": "UruguayNaturalTV.ar",
        "evento": "Uruguay Natural TV",
        "hora_inicio": "12:00",
        "hora_fin": "16:00",
        "progreso": 8
    },
    {
        "canal": "Venus.ar",
        "evento": "Big Natural Vixens Aim to Please",
        "hora_inicio": "11:57",
        "hora_fin": "13:28",
        "progreso": 24
    },
    {
        "canal": "Volver.ar",
        "evento": "Karlos Arguiñano en tu cocina",
        "hora_inicio": "12:00",
        "hora_fin": "13:00",
        "progreso": 32
    },
    {
        "canal": "VTV.ar",
        "evento": "Valor agregado",
        "hora_inicio": "12:00",
        "hora_fin": "13:00",
        "progreso": 32
    },
    {
        "canal": "WarnerChannel.ar",
        "evento": "Dos hombres y medio",
        "hora_inicio": "12:01",
        "hora_fin": "12:25",
        "progreso": 77
    },
    {
        "canal": "ZooMoo.ar",
        "evento": "ZooMoo tiene cerebro",
        "hora_inicio": "12:15",
        "hora_fin": "12:30",
        "progreso": 29
    }
]